Workbook

Sheet Capital & Ownership
B1: LOKA — CAPITAL, OWNERSHIP & PRE-OPENING EXPENSES
B2: Last updated: 1 Jul 2026 | Capital, Acquisition, Pre-Opening, Renovation CapEx & Operations↔Capital
B4: A. OWNERSHIP STRUCTURE
B5: Owner | C5: Share % | D5: Capital ($) | E5: Expenses ($) | F5: Remaining ($) | G5: Role / Notes
B6: Lohith Reddy | C6: 0.5 | D6: 300000 | E6: =D67 | F6: =D6-E6 | G6: 50% — Managing Partner
B7: Kashigoud Patil | C7: 0.3 | D7: 180000 | E7: =D52 | F7: =D7-E7 | G7: 30% — Partner
B8: Shashirekha Basavaraju | C8: 0.2 | D8: 120000 | E8: =D82 | F8: =D8-E8 | G8: 20% — Partner
B9: TOTAL | C9: =SUM(C6:C8) | D9: =SUM(D6:D8) | E9: =SUM(E6:E8) | F9: =SUM(F6:F8)
B11: B. RESTAURANT ACQUISITION — $390,000 TOTAL
B12: Description | C12: Date | D12: Amount ($) | E12: Paid By | F12: Status | G12: Notes
B13: TOTAL Purchase Price — Previous Owners | D13: 390000 | E13: All Partners | F13: ⚠️ PARTIALLY PAID — $2,235 remaining | G13: Full acquisition amount
B14: Advance Payment (paid by Lohith) | D14: 5000 | E14: Lohith Reddy | F14: ✅ PAID | G14: Advance to previous owners
B15: Payment to Previous Owners | C15: 46176 | D15: 95000 | E15: Lohith Reddy | F15: ✅ PAID | G15: Paid from restaurant operating balance — 3 Jun 2026
B16: Payment to Previous Owner — Account 1 | C16: 46177 | D16: 8000 | E16: Lohith Reddy | F16: ✅ PAID | G16: Capital payment — from main budget — transferred to different accounts
B17: Payment to Previous Owner — Account 2 | C17: 46177 | D17: 4500 | E17: Lohith Reddy | F17: ✅ PAID | G17: Capital payment — from main budget — transferred to different account
B18: Payment to Previous Owner — Account 3 | C18: 46177 | D18: 15000 | E18: Lohith Reddy | F18: ✅ PAID | G18: Capital payment — from main budget — transferred to different accounts
B19: Payment to Previous Owner — Account 4 | C19: 46177 | D19: 10000 | E19: Lohith Reddy | F19: ✅ PAID | G19: Capital payment — from main budget — transferred to different accounts
B20: Payment to Previous Owner — Account 5 | C20: 46177 | D20: 44000 | E20: Lohith Reddy | F20: ✅ PAID | G20: Capital payment — from main budget — transferred to different accounts
B21: Payment to Previous Owner — Account 6 | C21: 46177 | D21: 44000 | E21: Lohith Reddy | F21: ✅ PAID | G21: Capital payment — from main budget — transferred to different accounts
B22: Payment to Previous Owner — Jun 5 | C22: 46178 | D22: 30000 | E22: Lohith Reddy | F22: ✅ PAID | G22: Transfer — 5 Jun 2026
B23: Payment to Previous Owners — Jun 19 (a) | C23: 46192 | D23: 30000 | E23: Lohith Reddy | F23: ✅ PAID | G23: Capital payment to previous owners — 19 Jun 2026
B24: Payment to Previous Owners — Jun 19 (b) | C24: 46192 | D24: 20735 | E24: Lohith Reddy | F24: ✅ PAID | G24: Capital payment to previous owners — 19 Jun 2026
B25: Electricity Bill (Mar–May CFE) — paid by Lohith for Previous Owners | C25: 46190 | D25: 15530 | E25: Lohith Reddy | F25: ✅ OFFSET vs balance | G25: Prev owners’ liability (pre-handover). Deducted from acquisition balance owed to them.
B26: Payment to Previous Owners — Jun 22 | C26: 46195 | D26: 60000 | E26: Lohith Reddy | F26: ✅ PAID | G26: Capital payment to previous owners — 22 Jun 2026
B27: Additional Payment to Previous Owners — Jun 30 | C27: 46203 | D27: 6000 | E27: Lohith Reddy | F27: ✅ PAID | G27: Additional capital payment to previous owners — 30 Jun 2026 (part of $16k transfer; rent portion logged separately)
B31: Balance Remaining | D31: =D13-SUM(D14:D30) | E31: — | F31: ⏳ PENDING | G31: $390,000 − $372,235 paid (Jun 3–30) − $15,530 electricity offset = $2,235 remaining
B33: PAYMENT BREAKDOWN — How the $390,000 will be funded
B34: Source | C34: From | D34: Amount ($) | E34: Toward % | F34: Cumulative | G34: Notes
B35: Kashigoud Transfer to Lohith | C35: Kashigoud Patil | D35: 125000 | E35: =D35/390000 | F35: =D35 | G35: Full Kashi transfer
B36: Shashirekha Transfer to Lohith | C36: Shashirekha B. | D36: 100000 | E36: =D36/390000 | F36: =D35+D36 | G36: Full Shashi transfer
B37: Lohith Reddy (own funds) | C37: Lohith Reddy | D37: =390000-D35-D36 | E37: =D37/390000 | F37: =D35+D36+D37 | G37: Balance from Lohith
B38: Advance Already Paid | C38: Lohith Reddy | D38: 5000 | E38: =D38/390000 | F38: Paid ✅ | G38: Already paid
B40: C. PRE-OPENING EXPENSES — KASHIGOUD PATIL
B41: Description | C41: Date | D41: Amount ($) | E41: Paid To | F41: Category | G41: Notes
B42: Transfer to Lohith Reddy (capital allocation) | D42: 145000 | E42: Bank → Lohith | F42: Internal Transfer | G42: For acquisition & expenses; $125,000 initial + $20,000 transferred 29 Jun 2026 = $145,000
B43: Soft Restaurant License & Tools | D43: 15195 | E43: Soft App | F43: Software / License | G43: POS + mgmt tools
B44: Mercado Pago Terminal | D44: 500 | E44: Soft App / MP | F44: POS Hardware | G44: MP card reader terminal fee
B45: Camera Cloud Recording — 7 Day Continuous (28 May) | C45: 46170 | D45: 436.12 | E45: Kashigoud Patil (VISA ••••9193) | F45: Technology / Security | G45: Shenzhen Tange — cloud CCTV recording 1yr — US$23.90 = MXN $436.12
B46: Camera Cloud Recording — 7 Day Continuous (29 May) | C46: 46171 | D46: 437.22 | E46: Kashigoud Patil (VISA ••••9193) | F46: Technology / Security | G46: Shenzhen Tange — cloud CCTV recording 1yr — US$23.90 = MXN $437.22
B52: KASHIGOUD TOTAL | D52: =SUM(D42:D51)
B54: D. PRE-OPENING EXPENSES — LOHITH REDDY
B55: Description | C55: Date | D55: Amount ($) | E55: Paid To | F55: Category | G55: Notes
B56: Advance Payment to Previous Owners | D56: 5000 | E56: Previous Owners | F56: Acquisition | G56: 5k advance on 390k purchase
B57: Notary Fees | D57: 15797 | E57: Notary Office | F57: Legal | G57: Legal fees for restaurant acquisition
B58: Poliza Juridica (Legal Policy) | D58: 5150 | E58: Legal / Insurance | F58: Legal | G58: Poliza Juridica — legal insurance policy
B59: Alejandra — Documentation Asst. | D59: 3000 | E59: Alejandra | F59: Professional Services | G59: Documentation & legal assistance — pre-opening
B60: Alejandra — License Costs | C60: 46190 | D60: 1400 | E60: Alejandra | F60: Legal / License | G60: License costs — paid by Lohith 17 Jun
B61: Reimbursement to Shashirekha (over-budget expenses) | C61: 46210 | D61: 1034 | E61: Shashirekha B. | F61: Partner Settlement | G61: Reimbursed Shashi for spending $1,034 over her $120k budget (menu + syrup) — 7 Jul 2026
B67: LOHITH TOTAL | D67: =SUM(D56:D66)
B69: E. PRE-OPENING EXPENSES — SHASHIREKHA BASAVARAJU
B70: Description | C70: Date | D70: Amount ($) | E70: Paid To | F70: Category | G70: Notes
B71: Transfer to Lohith Reddy (capital allocation) | D71: 100000 | E71: Bank → Lohith | F71: Internal Transfer | G71: For acquisition & expenses
B72: Temu items | D72: 2646 | E72: Temu | F72: Equipment / Supplies | G72: Temu items — restaurant supplies & equipment
B73: Board games for restaurant ambiance | D73: 745 | E73: Various | F73: Equipment / Decor | G73: Board games for restaurant ambiance
B74: Special menu board | D74: 204 | E74: Sign Maker | F74: Branding / Signage | G74: Special menu board
B75: Logo and sticker printing | D75: 845 | E75: Print Shop | F75: Branding / Signage | G75: Logo and sticker printing
B76: Sign boards, stationary, other decor | D76: 1555 | E76: China Shop | F76: Decor / Signage | G76: Sign boards, stationary, other decor
B77: Logo Box Repair / Fix | C77: 46176 | D77: 900 | E77: Supplier | F77: Branding / Signage | G77: Logo box repair — paid by Shashirekha
B78: Letrero 3-D Retroiluminado (illuminated sign) | C78: 46190 | D78: 12000 | E78: POPA Publicidad | F78: Branding / Signage | G78: 3D backlit sign + "CAFE RESTAURANT & BAR" letters — paid by Shashirekha · Cotización A0626-560
B79: Menu printing | C79: 46210 | D79: 1219 | E79: Print Shop | F79: Branding / Printing | G79: Printed menus — paid by Shashirekha (post-opening)
B80: Syrup bottles | C80: 46210 | D80: 920 | E80: Supplier | F80: Equipment / Supplies | G80: Syrup bottles — paid by Shashirekha (post-opening)
B81: Reimbursement received from Lohith (over-budget) | C81: 46210 | D81: -1034 | E81: Lohith Reddy | F81: Partner Settlement | G81: Received $1,034 back from Lohith for over-budget spend — nets Shashi to her $120k budget
B82: SHASHIREKHA TOTAL | D82: =SUM(D71:D81)
B84: F. GRAND SUMMARY — CAPITAL DEPLOYMENT
B85: Line Item
B86: Total Budget | C86: =SUM(D6:D8) | E86: 100% of committed capital
B87: Acquisition Total | C87: =D13 | D87: =C87/C86 | E87: To be paid to previous owners
B88: Advance Paid | C88: =D14 | D88: =C88/C86 | E88: ✅ Already paid
B89: Balance Remaining | C89: =D31 | D89: =C89/C86 | E89: ⏳ Pending — funded by transfers
B90: Kashi Ops (excl tr) | C90: =SUM(D43:D44) | D90: =C90/C86 | E90: Soft license + terminal
B91: Kashi Transfer | C91: =D42 | D91: =C91/C86
B92: Lohith Pre-Opening | C92: =D67 | D92: =C92/C86 | E92: Advance + Notary + Poliza + Alejandra
B93: Shashi Transfer | C93: =D71 | D93: =C93/C86
B94: Shashi Other Exp | C94: =SUM(D72:D81) | D94: =C94/C86 | E94: Yellow rows above
B95: Total Cash Out | C95: =C87+C90+C92+C94+C97 | D95: =C95/C86 | E95: Actual cash leaving the partnership
B96: Remaining Budget | C96: =C86-C95 | D96: =C96/C86
B97: Renovation & Post-Opening CapEx | C97: =D129 | D97: =C97/C86 | E97: Section I (bottom of sheet)
B98: G. REMAINING TRANSFERS DUE TO LOHITH REDDY
B99: Partner | C99: Total Budget ($) | D99: Already Transferred ($) | E99: Direct Expenses ($) | F99: Still Owed to Lohith ($) | G99: Status
B100: Kashigoud Patil | C100: =D7 | D100: =D42 | E100: =SUM(D43:D51) | F100: =C100-D100-E100 | G100: ⏳ PENDING
B101: Shashirekha Basavaraju | C101: =D8 | D101: =D71 | E101: =SUM(D72:D81) | F101: =C101-D101-E101 | G101: ⏳ PENDING
B102: TOTAL | C102: =C100+C101 | D102: =D100+D101 | E102: =E100+E101 | F102: =F100+F101
B104: H. ACQUISITION PAYMENT — SPLIT BY OWNERSHIP SHARE (50% / 30% / 20%)
B105: Partner | C105: Share % | D105: Share of $390k Total ($) | E105: Paid So Far — by Share ($) | F105: Share of Balance Remaining ($) | G105: Status
B106: Lohith Reddy | C106: =C6 | D106: =C106*D13 | E106: =C106*$D$138 | F106: =D106-E106 | G106: =IF(F106<1,"✅ Share fully paid","⏳ $"&TEXT(F106,"#,##0")&" of share remaining")
B107: Kashigoud Patil | C107: =C7 | D107: =C107*D13 | E107: =C107*$D$138 | F107: =D107-E107 | G107: =IF(F107<1,"✅ Share fully paid","⏳ $"&TEXT(F107,"#,##0")&" of share remaining")
B108: Shashirekha Basavaraju | C108: =C8 | D108: =C108*D13 | E108: =C108*$D$138 | F108: =D108-E108 | G108: =IF(F108<1,"✅ Share fully paid","⏳ $"&TEXT(F108,"#,##0")&" of share remaining")
B109: TOTAL | C109: 1 | D109: =D106+D107+D108 | E109: =E106+E107+E108 | F109: =F106+F107+F108 | G109: =IF(F109=0,"✅ Fully Paid","⏳ Balance: $"&TEXT(F109,"#,##0"))
B112: I. RENOVATION & CAPITAL EXPENSES — POST-OPENING
B113: Description | C113: Date | D113: Amount ($) | E113: Paid By | F113: Category | G113: Status | H113: Notes
B129: RENOVATION / CAPEX TOTAL | D129: =SUM(D114:D128)
B130: Log renovation/equipment here with Paid By for partner settlement. If also logged in 💸 Expenses, tag category "Capital Expense — …" so it stays OUT of Daily Log operating costs.
B132: J. LOHITH — CASH POSITION (funds managed: own budget + partner transfers)
B133: My Total Budget | D133: =D6
B134: + Kashigoud Transferred to Me | D134: =D42
B135: + Shashirekha Transferred to Me | D135: =D71
B136: =Total Funds In | D136: =D133+D134+D135
B137: − Pre-Opening Expenses (excl. $5k advance) | D137: =D67-D56
B138: − Paid to Previous Owners (incl. $15,530 electricity offset) | D138: =SUM(D14:D30)
B139: − Operating costs funded from capital (ledger settlement + rent) | D139: =C147
...

Sheet 📊 Dashboard
A2: 🍽️ LOKA Cafe Restaurante | H2: Restaurant Manager — powered by Soft + Excel
B5: 📌 HOW TO USE: ① Each update, go to 📅 Daily Log → enter Date + Revenue + Orders from Soft App ② Fill 💸 Expenses for costs paid ③ Update 📦 Inventory when stock changes ④ This dashboard updates automatically
B7: 💰 REVENUE (auto-pulled from Daily Log)
B9: TODAY'S REVENUE | D9: WEEK REVENUE | F9: MONTH REVENUE | H9: TODAY'S EXPENSES | J9: TODAY'S NET PROFIT | L9: AVG TICKET
B10: ='📅 Daily Log'!F6 | D10: ='📅 Daily Log'!N6 | F10: ='📅 Daily Log'!O6 | H10: ='📅 Daily Log'!H6 | J10: ='📅 Daily Log'!I6 | L10: =IFERROR('📅 Daily Log'!F6/'📅 Daily Log'!G6,0)
B14: 📊 OPERATIONS
B16: TODAY'S ORDERS | D16: WEEK ORDERS | F16: PROFIT MARGIN % | H16: LOW STOCK ITEMS | J16: WEEK EXPENSES | L16: PENDING ORDERS
B17: ='📅 Daily Log'!G6 | D17: =IFERROR(SUMPRODUCT((ISNUMBER('📅 Daily Log'!$B$8:$B$500))*('📅 Daily Log'!$B$8:$B$500>=TODAY()-MOD(TODAY()-2,7))*('📅 Daily Log'!$B$8:$B$500<TODAY()-MOD(TODAY()-2,7)+7)*IF(ISNUMBER('📅 Daily Log'!$G$8:$G$500),'📅 Daily Log'!$G$8:$G$500,0)),0) | F17: =IFERROR('📅 Daily Log'!J6,0) | H17: ='📦 Inventory'!H5 | J17: ='📅 Daily Log'!P6 | L17: ='🚚 Suppliers'!H5
B21: 📅 LAST 10 DAYS (from Daily Log — updates automatically)
B22: Date | C22: Day | D22: Revenue ($) | E22: Orders | F22: Avg Ticket | G22: Expenses ($) | H22: Net Profit ($) | I22: Margin % | J22: Notes | K22: vs Prev Day
B23: ='📅 Daily Log'!B8 | C23: ='📅 Daily Log'!F8 | D23: ='📅 Daily Log'!G8 | E23: =IFERROR('📅 Daily Log'!F8/'📅 Daily Log'!G8,0) | F23: ='📅 Daily Log'!H8 | G23: ='📅 Daily Log'!I8 | H23: ='📅 Daily Log'!J8 | I23: ='📅 Daily Log'!K8 | J23: ='📅 Daily Log'!K8 | K23: —
B24: ='📅 Daily Log'!B9 | C24: ='📅 Daily Log'!F9 | D24: ='📅 Daily Log'!G9 | E24: =IFERROR('📅 Daily Log'!F9/'📅 Daily Log'!G9,0) | F24: ='📅 Daily Log'!H9 | G24: ='📅 Daily Log'!I9 | H24: ='📅 Daily Log'!J9 | I24: ='📅 Daily Log'!K9 | J24: ='📅 Daily Log'!K9 | K24: =IFERROR(IF(D24>D23,"▲ +"&TEXT(D24-D23,"$#,##0"),IF(D24<D23,"▼ "&TEXT(D24-D23,"$#,##0"),"— same")),"")
B25: ='📅 Daily Log'!B10 | C25: ='📅 Daily Log'!F10 | D25: ='📅 Daily Log'!G10 | E25: =IFERROR('📅 Daily Log'!F10/'📅 Daily Log'!G10,0) | F25: ='📅 Daily Log'!H10 | G25: ='📅 Daily Log'!I10 | H25: ='📅 Daily Log'!J10 | I25: ='📅 Daily Log'!K10 | J25: ='📅 Daily Log'!K10 | K25: =IFERROR(IF(D25>D24,"▲ +"&TEXT(D25-D24,"$#,##0"),IF(D25<D24,"▼ "&TEXT(D25-D24,"$#,##0"),"— same")),"")
B26: ='📅 Daily Log'!B11 | C26: ='📅 Daily Log'!F11 | D26: ='📅 Daily Log'!G11 | E26: =IFERROR('📅 Daily Log'!F11/'📅 Daily Log'!G11,0) | F26: ='📅 Daily Log'!H11 | G26: ='📅 Daily Log'!I11 | H26: ='📅 Daily Log'!J11 | I26: ='📅 Daily Log'!K11 | J26: ='📅 Daily Log'!K11 | K26: =IFERROR(IF(D26>D25,"▲ +"&TEXT(D26-D25,"$#,##0"),IF(D26<D25,"▼ "&TEXT(D26-D25,"$#,##0"),"— same")),"")
B27: ='📅 Daily Log'!B12 | C27: ='📅 Daily Log'!F12 | D27: ='📅 Daily Log'!G12 | E27: =IFERROR('📅 Daily Log'!F12/'📅 Daily Log'!G12,0) | F27: ='📅 Daily Log'!H12 | G27: ='📅 Daily Log'!I12 | H27: ='📅 Daily Log'!J12 | I27: ='📅 Daily Log'!K12 | J27: ='📅 Daily Log'!K12 | K27: =IFERROR(IF(D27>D26,"▲ +"&TEXT(D27-D26,"$#,##0"),IF(D27<D26,"▼ "&TEXT(D27-D26,"$#,##0"),"— same")),"")
B28: ='📅 Daily Log'!B13 | C28: ='📅 Daily Log'!F13 | D28: ='📅 Daily Log'!G13 | E28: =IFERROR('📅 Daily Log'!F13/'📅 Daily Log'!G13,0) | F28: ='📅 Daily Log'!H13 | G28: ='📅 Daily Log'!I13 | H28: ='📅 Daily Log'!J13 | I28: ='📅 Daily Log'!K13 | J28: ='📅 Daily Log'!K13 | K28: =IFERROR(IF(D28>D27,"▲ +"&TEXT(D28-D27,"$#,##0"),IF(D28<D27,"▼ "&TEXT(D28-D27,"$#,##0"),"— same")),"")
B29: ='📅 Daily Log'!B14 | C29: ='📅 Daily Log'!F14 | D29: ='📅 Daily Log'!G14 | E29: =IFERROR('📅 Daily Log'!F14/'📅 Daily Log'!G14,0) | F29: ='📅 Daily Log'!H14 | G29: ='📅 Daily Log'!I14 | H29: ='📅 Daily Log'!J14 | I29: ='📅 Daily Log'!K14 | J29: ='📅 Daily Log'!K14 | K29: =IFERROR(IF(D29>D28,"▲ +"&TEXT(D29-D28,"$#,##0"),IF(D29<D28,"▼ "&TEXT(D29-D28,"$#,##0"),"— same")),"")
B30: ='📅 Daily Log'!B15 | C30: ='📅 Daily Log'!F15 | D30: ='📅 Daily Log'!G15 | E30: =IFERROR('📅 Daily Log'!F15/'📅 Daily Log'!G15,0) | F30: ='📅 Daily Log'!H15 | G30: ='📅 Daily Log'!I15 | H30: ='📅 Daily Log'!J15 | I30: ='📅 Daily Log'!K15 | J30: ='📅 Daily Log'!K15 | K30: =IFERROR(IF(D30>D29,"▲ +"&TEXT(D30-D29,"$#,##0"),IF(D30<D29,"▼ "&TEXT(D30-D29,"$#,##0"),"— same")),"")
B31: ='📅 Daily Log'!B16 | C31: ='📅 Daily Log'!F16 | D31: ='📅 Daily Log'!G16 | E31: =IFERROR('📅 Daily Log'!F16/'📅 Daily Log'!G16,0) | F31: ='📅 Daily Log'!H16 | G31: ='📅 Daily Log'!I16 | H31: ='📅 Daily Log'!J16 | I31: ='📅 Daily Log'!K16 | J31: ='📅 Daily Log'!K16 | K31: =IFERROR(IF(D31>D30,"▲ +"&TEXT(D31-D30,"$#,##0"),IF(D31<D30,"▼ "&TEXT(D31-D30,"$#,##0"),"— same")),"")
B32: ='📅 Daily Log'!B17 | C32: ='📅 Daily Log'!F17 | D32: ='📅 Daily Log'!G17 | E32: =IFERROR('📅 Daily Log'!F17/'📅 Daily Log'!G17,0) | F32: ='📅 Daily Log'!H17 | G32: ='📅 Daily Log'!I17 | H32: ='📅 Daily Log'!J17 | I32: ='📅 Daily Log'!K17 | J32: ='📅 Daily Log'!K17 | K32: =IFERROR(IF(D32>D31,"▲ +"&TEXT(D32-D31,"$#,##0"),IF(D32<D31,"▼ "&TEXT(D32-D31,"$#,##0"),"— same")),"")
B34: ⚠️ INVENTORY ALERTS (from Inventory sheet)
B35: Ingredient | F35: Min Level | H35: Status | J35: Action Needed
B36: ='📦 Inventory'!B9 | E36: ='📦 Inventory'!E9 | G36: ='📦 Inventory'!F9 | I36: ='📦 Inventory'!J9 | K36: =IF('📦 Inventory'!E9=0,"🚫 Order immediately",IF('📦 Inventory'!E9<='📦 Inventory'!F9,"⚠️ Reorder soon","✅ OK"))
B37: ='📦 Inventory'!B10 | E37: ='📦 Inventory'!E10 | G37: ='📦 Inventory'!F10 | I37: ='📦 Inventory'!J10 | K37: =IF('📦 Inventory'!E10=0,"🚫 Order immediately",IF('📦 Inventory'!E10<='📦 Inventory'!F10,"⚠️ Reorder soon","✅ OK"))
B38: ='📦 Inventory'!B11 | E38: ='📦 Inventory'!E11 | G38: ='📦 Inventory'!F11 | I38: ='📦 Inventory'!J11 | K38: =IF('📦 Inventory'!E11=0,"🚫 Order immediately",IF('📦 Inventory'!E11<='📦 Inventory'!F11,"⚠️ Reorder soon","✅ OK"))
B39: ='📦 Inventory'!B12 | E39: ='📦 Inventory'!E12 | G39: ='📦 Inventory'!F12 | I39: ='📦 Inventory'!J12 | K39: =IF('📦 Inventory'!E12=0,"🚫 Order immediately",IF('📦 Inventory'!E12<='📦 Inventory'!F12,"⚠️ Reorder soon","✅ OK"))
B40: ='📦 Inventory'!B13 | E40: ='📦 Inventory'!E13 | G40: ='📦 Inventory'!F13 | I40: ='📦 Inventory'!J13 | K40: =IF('📦 Inventory'!E13=0,"🚫 Order immediately",IF('📦 Inventory'!E13<='📦 Inventory'!F13,"⚠️ Reorder soon","✅ OK"))
B42: 💼 CAPITAL & ACQUISITION STATUS — live from Capital & Ownership sheet
B44: TOTAL BUDGET | D44: TOTAL CASH OUT | F44: REMAINING BUDGET | H44: ACQUISITION PRICE | J44: ADVANCE PAID | L44: BALANCE PENDING
B45: ='Capital & Ownership'!C75 | D45: ='Capital & Ownership'!C86 | F45: ='Capital & Ownership'!C87 | H45: ='Capital & Ownership'!C76 | J45: ='Capital & Ownership'!C77 | L45: ='Capital & Ownership'!C78
B46: All 3 partners | D46: Excl. internal transfers | F46: Available for operations | H46: To previous owners | J46: ✅ Paid by Lohith | L46: ⏳ Outstanding
B48: 👥 OWNER CAPITAL SUMMARY
B49: OWNER | D49: SHARE % | F49: CAPITAL ($) | G49: ROLE | H49: EXPENSES ($) | J49: REMAINING ($) | L49: % SPENT
B50: ='Capital & Ownership'!B6 | D50: ='Capital & Ownership'!C6 | F50: ='Capital & Ownership'!D6 | G50: 50% — Managing Partner | H50: ='Capital & Ownership'!E6 | J50: ='Capital & Ownership'!F6 | L50: =IFERROR('Capital & Ownership'!E6/'Capital & Ownership'!D6,0)
B51: ='Capital & Ownership'!B7 | D51: ='Capital & Ownership'!C7 | F51: ='Capital & Ownership'!D7 | G51: 30% — Partner | H51: ='Capital & Ownership'!E7 | J51: ='Capital & Ownership'!F7 | L51: =IFERROR('Capital & Ownership'!E7/'Capital & Ownership'!D7,0)
B52: ='Capital & Ownership'!B8 | D52: ='Capital & Ownership'!C8 | F52: ='Capital & Ownership'!D8 | G52: 20% — Partner | H52: ='Capital & Ownership'!E8 | J52: ='Capital & Ownership'!F8 | L52: =IFERROR('Capital & Ownership'!E8/'Capital & Ownership'!D8,0)
B53: TOTAL | D53: ='Capital & Ownership'!C9 | F53: ='Capital & Ownership'!D9 | H53: ='Capital & Ownership'!E9 | J53: ='Capital & Ownership'!F9 | L53: =IFERROR('Capital & Ownership'!E9/'Capital & Ownership'!D9,0)
B55: 🧾 PRE-OPENING EXPENSES BREAKDOWN
B56: EXPENSE ITEM | E56: PAID BY | G56: AMOUNT ($) | I56: CATEGORY | K56: STATUS
B57: ='Capital & Ownership'!B13 | E57: All Partners | G57: ='Capital & Ownership'!D13 | I57: Acquisition | K57: ⚠️ Not Fully Paid
B58: ='Capital & Ownership'!B14 | E58: Lohith Reddy | G58: ='Capital & Ownership'!D14 | I58: Acquisition Advance | K58: ✅ Paid
B59: ='Capital & Ownership'!B35 | E59: Kashigoud Patil | G59: ='Capital & Ownership'!D35 | I59: Software / License | K59: ✅ Paid
B60: ='Capital & Ownership'!B36 | E60: Kashigoud Patil | G60: ='Capital & Ownership'!D36 | I60: Equipment | K60: ✅ Paid
B61: ='Capital & Ownership'!B47 | E61: Lohith Reddy | G61: ='Capital & Ownership'!D47 | I61: Legal / Notary | K61: ✅ Paid
B62: ='Capital & Ownership'!B50 | E62: Lohith Reddy | G62: ='Capital & Ownership'!D50 | I62: Legal / Insurance | K62: ✅ Paid
B63: ='Capital & Ownership'!B51 | E63: Lohith Reddy | G63: ='Capital & Ownership'!D51 | I63: Professional Services | K63: ✅ Paid
B64: ℹ️ Internal transfers: Kashigoud → Lohith $125,000 | Shashirekha → Lohith $100,000 (not counted as expenses — capital reallocation only)

Sheet 📅 Daily Log
A2: 📅 LOKA — DAILY LOG | I2: Enter 2 values from Soft App each day → everything else calculates
B5: ✏️ INSTRUCTIONS: Each time you open this file, add a new row below. Fill only the BLUE cells: 📌 Date | 💰 Revenue (from Soft App end-of-day report) | 🛒 Orders (from Soft App) | 📝 Notes (optional). All other columns calculate automatically.
F6: =SUMIFS($D$8:$D$500,$B$8:$B$500,TODAY())+SUMIFS($E$8:$E$500,$B$8:$B$500,TODAY())+SUMIFS($G$8:$G$500,$B$8:$B$500,TODAY()) | G6: =SUMIFS($G$8:$G$500,$B$8:$B$500,TODAY()) | H6: =SUMIFS($H$8:$H$500,$B$8:$B$500,TODAY()) | I6: =F6-H6 | J6: =IFERROR(I6/F6,0) | M6: =SUMPRODUCT((ISNUMBER($B$8:$B$500))*($B$8:$B$500>=TODAY()-MOD(TODAY()-2,7))*($B$8:$B$500<TODAY()-MOD(TODAY()-2,7)+7)*IF(ISNUMBER($F$8:$F$500),$F$8:$F$500,0)) | N6: =SUMPRODUCT((ISNUMBER($B$8:$B$500))*($B$8:$B$500>=TODAY()-MOD(TODAY()-2,7))*($B$8:$B$500<TODAY()-MOD(TODAY()-2,7)+7)*IF(ISNUMBER($F$8:$F$500),$F$8:$F$500,0)) | O6: =SUMPRODUCT((ISNUMBER($B$8:$B$500))*(MONTH($B$8:$B$500)=MONTH(TODAY()))*(YEAR($B$8:$B$500)=YEAR(TODAY()))*IF(ISNUMBER($F$8:$F$500),$F$8:$F$500,0)) | P6: =SUMPRODUCT((ISNUMBER($B$8:$B$500))*($B$8:$B$500>=TODAY()-MOD(TODAY()-2,7))*($B$8:$B$500<TODAY()-MOD(TODAY()-2,7)+7)*IF(ISNUMBER($H$8:$H$500),$H$8:$H$500,0)) | Q6: =M6-P6
B7: Date | C7: Day | D7: Card / Mercado Pago ($) | E7: Cash ($) | F7: Total Revenue ($) | G7: Transfer ($) | H7: Expenses $ | I7: Net Profit $ | J7: Margin % | K7: Notes | L7: Source | M7: WEEK PROFIT | N7: CUMUL. REVENUE | O7: MONTH REVENUE | P7: Week Expenses | Q7: Week Profit | R7: MP Comm $ | S7: MP Rate | T7: 0.0406 | U7: Soft Rest Card $ | V7: Soft Comm $ | W7: Soft Rate | X7: 0.0205
B8: 46160 | C8: Mon | D8: 2229 | E8: 1460 | F8: =IFERROR(D8+E8+G8,0) | H8: =SUMIFS('💸 Expenses'!$F$8:$F$500,'💸 Expenses'!$B$8:$B$500,">="&B8,'💸 Expenses'!$B$8:$B$500,"<"&(B8+1)) | I8: =IFERROR(F8-H8,0) | J8: =IFERROR(I8/F8,0) | L8: Manual Bills | R8: =IFERROR(D8*$T$7,0)
B9: 46161 | C9: Tue | D9: 2125 | E9: 1729 | F9: =IFERROR(D9+E9+G9,0) | H9: =SUMIFS('💸 Expenses'!$F$8:$F$500,'💸 Expenses'!$B$8:$B$500,">="&B9,'💸 Expenses'!$B$8:$B$500,"<"&(B9+1)) | I9: =IFERROR(F9-H9,0) | J9: =IFERROR(I9/F9,0) | L9: Manual Bills | R9: =IFERROR(D9*$T$7,0)
B10: 46162 | C10: Wed | D10: 1459 | E10: 2665 | F10: =IFERROR(D10+E10+G10,0) | H10: =SUMIFS('💸 Expenses'!$F$8:$F$500,'💸 Expenses'!$B$8:$B$500,">="&B10,'💸 Expenses'!$B$8:$B$500,"<"&(B10+1)) | I10: =IFERROR(F10-H10,0) | J10: =IFERROR(I10/F10,0) | L10: Manual Bills | R10: =IFERROR(D10*$T$7,0)
B11: 46163 | C11: Thu | D11: 2570 | E11: 2163 | F11: =IFERROR(D11+E11+G11,0) | H11: =SUMIFS('💸 Expenses'!$F$8:$F$500,'💸 Expenses'!$B$8:$B$500,">="&B11,'💸 Expenses'!$B$8:$B$500,"<"&(B11+1)) | I11: =IFERROR(F11-H11,0) | J11: =IFERROR(I11/F11,0) | L11: Manual Bills | R11: =IFERROR(D11*$T$7,0)
B12: 46164 | C12: Fri | D12: 1959 | E12: 2323 | F12: =IFERROR(D12+E12+G12,0) | H12: =SUMIFS('💸 Expenses'!$F$8:$F$500,'💸 Expenses'!$B$8:$B$500,">="&B12,'💸 Expenses'!$B$8:$B$500,"<"&(B12+1)) | I12: =IFERROR(F12-H12,0) | J12: =IFERROR(I12/F12,0) | L12: Manual Bills | R12: =IFERROR(D12*$T$7,0)
B13: 46165 | C13: Sat | D13: 2044 | E13: 1758 | F13: =IFERROR(D13+E13+G13,0) | H13: =SUMIFS('💸 Expenses'!$F$8:$F$500,'💸 Expenses'!$B$8:$B$500,">="&B13,'💸 Expenses'!$B$8:$B$500,"<"&(B13+1)) | I13: =IFERROR(F13-H13,0) | J13: =IFERROR(I13/F13,0) | K13: Payroll week — John $3,250 + Debi $1,500 + Victor $666 + Tips $1,198 | L13: Manual Bills | R13: =IFERROR(D13*$T$7,0)
B14: 46166 | C14: Sun | E14: 1198 | F14: =IFERROR(D14+E14+G14,0) | H14: =SUMIFS('💸 Expenses'!$F$8:$F$500,'💸 Expenses'!$B$8:$B$500,">="&B14,'💸 Expenses'!$B$8:$B$500,"<"&(B14+1)) | I14: =IFERROR(F14-H14,0) | J14: =IFERROR(I14/F14,0) | K14: 🔴 CLOSED — Sunday. Expenses are prep purchases for the week ahead. | L14: Manual Bills | R14: =IFERROR(D14*$T$7,0)
B15: 46167 | C15: Mon | D15: 2106 | E15: 1624 | F15: =IFERROR(D15+E15+G15,0) | H15: =SUMIFS('💸 Expenses'!$F$8:$F$500,'💸 Expenses'!$B$8:$B$500,">="&B15,'💸 Expenses'!$B$8:$B$500,"<"&(B15+1)) | I15: =IFERROR(F15-H15,0) | J15: =IFERROR(I15/F15,0) | L15: Manual Bills | R15: =IFERROR(D15*$T$7,0)
B16: 46168 | C16: Tue | D16: 1909 | E16: 2355 | F16: =IFERROR(D16+E16+G16,0) | H16: =SUMIFS('💸 Expenses'!$F$8:$F$500,'💸 Expenses'!$B$8:$B$500,">="&B16,'💸 Expenses'!$B$8:$B$500,"<"&(B16+1)) | I16: =IFERROR(F16-H16,0) | J16: =IFERROR(I16/F16,0) | L16: Manual Bills | R16: =IFERROR(D16*$T$7,0)
B17: 46169 | C17: Wed | D17: 1956 | E17: 1665 | F17: =IFERROR(D17+E17+G17,0) | H17: =SUMIFS('💸 Expenses'!$F$8:$F$500,'💸 Expenses'!$B$8:$B$500,">="&B17,'💸 Expenses'!$B$8:$B$500,"<"&(B17+1)) | I17: =IFERROR(F17-H17,0) | J17: =IFERROR(I17/F17,0) | L17: Manual Bills | R17: =IFERROR(D17*$T$7,0)
B18: 46170 | C18: Thu | D18: 1501 | E18: 2569 | F18: =IFERROR(D18+E18+G18,0) | H18: =SUMIFS('💸 Expenses'!$F$8:$F$500,'💸 Expenses'!$B$8:$B$500,">="&B18,'💸 Expenses'!$B$8:$B$500,"<"&(B18+1)) | I18: =IFERROR(F18-H18,0) | J18: =IFERROR(I18/F18,0) | L18: Manual Bills | R18: =IFERROR(D18*$T$7,0)
B19: 46171 | C19: Fri | D19: 3369 | E19: 2717 | F19: =IFERROR(D19+E19+G19,0) | H19: =SUMIFS('💸 Expenses'!$F$8:$F$500,'💸 Expenses'!$B$8:$B$500,">="&B19,'💸 Expenses'!$B$8:$B$500,"<"&(B19+1)) | I19: =IFERROR(F19-H19,0) | J19: =IFERROR(I19/F19,0) | L19: Manual Bills | R19: =IFERROR(D19*$T$7,0)
B20: 46172 | C20: Sat | D20: 3457 | E20: 1146 | F20: =IFERROR(D20+E20+G20,0) | H20: =SUMIFS('💸 Expenses'!$F$8:$F$500,'💸 Expenses'!$B$8:$B$500,">="&B20,'💸 Expenses'!$B$8:$B$500,"<"&(B20+1)) | I20: =IFERROR(F20-H20,0) | J20: =IFERROR(I20/F20,0) | L20: Manual Bills | R20: =IFERROR(D20*$T$7,0)
B21: 46173 | C21: Sun | E21: 893 | F21: =IFERROR(D21+E21+G21,0) | H21: =SUMIFS('💸 Expenses'!$F$8:$F$500,'💸 Expenses'!$B$8:$B$500,">="&B21,'💸 Expenses'!$B$8:$B$500,"<"&(B21+1)) | I21: =IFERROR(F21-H21,0) | J21: =IFERROR(I21/F21,0) | L21: Manual Bills | R21: =IFERROR(D21*$T$7,0)
B22: 46174 | C22: Mon | D22: 3433 | E22: 1276 | F22: =IFERROR(D22+E22+G22,0) | G22: 310 | H22: =SUMIFS('💸 Expenses'!$F$8:$F$500,'💸 Expenses'!$B$8:$B$500,">="&B22,'💸 Expenses'!$B$8:$B$500,"<"&(B22+1)) | I22: =IFERROR(F22-H22,0) | J22: =IFERROR(I22/F22,0) | L22: Manual Bills | R22: =IFERROR(D22*$T$7,0)
B23: 46175 | C23: Tue | D23: 1240 | E23: 320 | F23: =IFERROR(D23+E23+G23,0) | G23: 283 | H23: =SUMIFS('💸 Expenses'!$F$8:$F$500,'💸 Expenses'!$B$8:$B$500,">="&B23,'💸 Expenses'!$B$8:$B$500,"<"&(B23+1)) | I23: =IFERROR(F23-H23,0) | J23: =IFERROR(I23/F23,0) | L23: Manual Bills | R23: =IFERROR(D23*$T$7,0)
B24: 46176 | C24: Wed | D24: 1853 | E24: 1939 | F24: =IFERROR(D24+E24+G24,0) | G24: 120 | H24: =SUMIFS('💸 Expenses'!$F$8:$F$500,'💸 Expenses'!$B$8:$B$500,">="&B24,'💸 Expenses'!$B$8:$B$500,"<"&(B24+1)) | I24: =IFERROR(F24-H24,0) | J24: =IFERROR(I24/F24,0) | L24: Manual Bills | R24: =IFERROR(D24*$T$7,0)
B25: 46177 | C25: Thu | D25: 2712 | E25: 1045 | F25: =IFERROR(D25+E25+G25,0) | H25: =SUMIFS('💸 Expenses'!$F$8:$F$500,'💸 Expenses'!$B$8:$B$500,">="&B25,'💸 Expenses'!$B$8:$B$500,"<"&(B25+1)) | I25: =IFERROR(F25-H25,0) | J25: =IFERROR(I25/F25,0) | L25: Manual Bills | R25: =IFERROR(D25*$T$7,0)
B26: 46178 | C26: Fri | D26: 2495 | E26: 1778 | F26: =IFERROR(D26+E26+G26,0) | G26: 135 | H26: =SUMIFS('💸 Expenses'!$F$8:$F$500,'💸 Expenses'!$B$8:$B$500,">="&B26,'💸 Expenses'!$B$8:$B$500,"<"&(B26+1)) | I26: =IFERROR(F26-H26,0) | J26: =IFERROR(I26/F26,0) | L26: Manual Bills | R26: =IFERROR(D26*$T$7,0)
B27: 46179 | C27: Sat | D27: 580 | E27: 1754 | F27: =IFERROR(D27+E27+G27,0) | H27: =SUMIFS('💸 Expenses'!$F$8:$F$500,'💸 Expenses'!$B$8:$B$500,">="&B27,'💸 Expenses'!$B$8:$B$500,"<"&(B27+1)) | I27: =IFERROR(F27-H27,0) | J27: =IFERROR(I27/F27,0) | L27: Manual Bills | R27: =IFERROR(D27*$T$7,0)
B28: 46180 | C28: Sun | F28: =IFERROR(D28+E28+G28,0) | H28: =SUMIFS('💸 Expenses'!$F$8:$F$500,'💸 Expenses'!$B$8:$B$500,">="&B28,'💸 Expenses'!$B$8:$B$500,"<"&(B28+1)) | I28: =IFERROR(F28-H28,0) | L28: Manual Bills | R28: =IFERROR(D28*$T$7,0)
B29: 46181 | C29: Mon | D29: 1778 | E29: 1850 | F29: =IFERROR(D29+E29+G29,0) | G29: 99 | H29: =SUMIFS('💸 Expenses'!$F$8:$F$500,'💸 Expenses'!$B$8:$B$500,">="&B29,'💸 Expenses'!$B$8:$B$500,"<"&(B29+1)) | I29: =IFERROR(F29-H29,0) | J29: =IFERROR(I29/F29,0) | L29: Manual Bills | R29: =IFERROR(D29*$T$7,0)
B30: 46182 | C30: Tue | D30: 930 | E30: 4480 | F30: =IFERROR(D30+E30+G30,0) | H30: =SUMIFS('💸 Expenses'!$F$8:$F$500,'💸 Expenses'!$B$8:$B$500,">="&B30,'💸 Expenses'!$B$8:$B$500,"<"&(B30+1)) | I30: =IFERROR(F30-H30,0) | J30: =IFERROR(I30/F30,0) | L30: Manual Bills | R30: =IFERROR(D30*$T$7,0)
B31: 46183 | C31: Wed | D31: 2506 | E31: 1759 | F31: =IFERROR(D31+E31+G31,0) | H31: =SUMIFS('💸 Expenses'!$F$8:$F$500,'💸 Expenses'!$B$8:$B$500,">="&B31,'💸 Expenses'!$B$8:$B$500,"<"&(B31+1)) | I31: =IFERROR(F31-H31,0) | J31: =IFERROR(I31/F31,0) | L31: Manual Bills | R31: =IFERROR(D31*$T$7,0)
B32: 46184 | C32: Thu | D32: 2075 | E32: 2091 | F32: =IFERROR(D32+E32+G32,0) | G32: 0 | H32: =SUMIFS('💸 Expenses'!$F$8:$F$500,'💸 Expenses'!$B$8:$B$500,">="&B32,'💸 Expenses'!$B$8:$B$500,"<"&(B32+1)) | I32: =IFERROR(F32-H32,0) | J32: =IFERROR(I32/F32,0) | L32: Cierre 11 Jun + receipts | R32: =IFERROR(D32*$T$7,0)
B33: 46185 | C33: Fri | D33: 2635 | E33: 3435 | F33: =IFERROR(D33+E33+G33,0) | G33: 0 | H33: =SUMIFS('💸 Expenses'!$F$8:$F$500,'💸 Expenses'!$B$8:$B$500,">="&B33,'💸 Expenses'!$B$8:$B$500,"<"&(B33+1)) | I33: =IFERROR(F33-H33,0) | J33: =IFERROR(I33/F33,0) | L33: Cierre 12 Jun + receipts | R33: =IFERROR(D33*$T$7,0)
B34: 46186 | C34: Sat | D34: 1005 | E34: 806 | F34: =IFERROR(D34+E34+G34,0) | G34: 0 | H34: =SUMIFS('💸 Expenses'!$F$8:$F$500,'💸 Expenses'!$B$8:$B$500,">="&B34,'💸 Expenses'!$B$8:$B$500,"<"&(B34+1)) | I34: =IFERROR(F34-H34,0) | J34: =IFERROR(I34/F34,0) | L34: Receipts + Week 4 payroll paid Sat | R34: =IFERROR(D34*$T$7,0)
B35: 46187 | C35: Sun | D35: 0 | E35: 0 | F35: =IFERROR(D35+E35+G35,0) | G35: 0 | H35: =SUMIFS('💸 Expenses'!$F$8:$F$500,'💸 Expenses'!$B$8:$B$500,">="&B35,'💸 Expenses'!$B$8:$B$500,"<"&(B35+1)) | I35: =IFERROR(F35-H35,0) | J35: =IFERROR(I35/F35,0) | L35: CLOSED (Sunday) — market/prep run, no revenue | R35: =IFERROR(D35*$T$7,0)
B36: 46188 | C36: Mon | D36: 2075 | E36: 2348 | F36: =IFERROR(D36+E36+G36,0) | G36: 0 | H36: =SUMIFS('💸 Expenses'!$F$8:$F$500,'💸 Expenses'!$B$8:$B$500,">="&B36,'💸 Expenses'!$B$8:$B$500,"<"&(B36+1)) | I36: =IFERROR(F36-H36,0) | J36: =IFERROR(I36/F36,0) | L36: Cierre 15 Jun + receipts | R36: =IFERROR(D36*$T$7,0)
B37: 46189 | C37: Tue | D37: 1841 | E37: 945 | F37: =IFERROR(D37+E37+G37,0) | G37: 0 | H37: =SUMIFS('💸 Expenses'!$F$8:$F$500,'💸 Expenses'!$B$8:$B$500,">="&B37,'💸 Expenses'!$B$8:$B$500,"<"&(B37+1)) | I37: =IFERROR(F37-H37,0) | J37: =IFERROR(I37/F37,0) | L37: Cierre 16 Jun + receipts | R37: =IFERROR(D37*$T$7,0)
B38: 46190 | C38: Wed | D38: 2123 | E38: 2281 | F38: =IFERROR(D38+E38+G38,0) | G38: 0 | H38: =SUMIFS('💸 Expenses'!$F$8:$F$500,'💸 Expenses'!$B$8:$B$500,">="&B38,'💸 Expenses'!$B$8:$B$500,"<"&(B38+1)) | I38: =IFERROR(F38-H38,0) | J38: =IFERROR(I38/F38,0) | L38: Cierre 17 Jun + receipts | R38: =IFERROR(D38*$T$7,0)
B39: 46191 | C39: Thu | D39: 2211 | E39: 1554 | F39: =IFERROR(D39+E39+G39,0) | G39: 400 | H39: =SUMIFS('💸 Expenses'!$F$8:$F$500,'💸 Expenses'!$B$8:$B$500,">="&B39,'💸 Expenses'!$B$8:$B$500,"<"&(B39+1)) | I39: =IFERROR(F39-H39,0) | J39: =IFERROR(I39/F39,0) | L39: Cierre 18 Jun + receipts | R39: =IFERROR(D39*$T$7,0)
B40: 46192 | C40: Fri | D40: 4179 | E40: 2505 | F40: =IFERROR(D40+E40+G40,0) | G40: 120 | H40: =SUMIFS('💸 Expenses'!$F$8:$F$500,'💸 Expenses'!$B$8:$B$500,">="&B40,'💸 Expenses'!$B$8:$B$500,"<"&(B40+1)) | I40: =IFERROR(F40-H40,0) | J40: =IFERROR(I40/F40,0) | L40: Cierre via loka.py | R40: =IFERROR(D40*$T$7,0)
B41: 46193 | C41: Sat | D41: 1172 | E41: 1079 | F41: =IFERROR(D41+E41+G41,0) | G41: 0 | H41: =SUMIFS('💸 Expenses'!$F$8:$F$500,'💸 Expenses'!$B$8:$B$500,">="&B41,'💸 Expenses'!$B$8:$B$500,"<"&(B41+1)) | I41: =IFERROR(F41-H41,0) | J41: =IFERROR(I41/F41,0) | L41: Cierre via loka.py | R41: =IFERROR(D41*$T$7,0)
B42: 46194 | C42: Sun | D42: 0 | E42: 0 | F42: =IFERROR(D42+E42+G42,0) | G42: 0 | H42: =SUMIFS('💸 Expenses'!$F$8:$F$500,'💸 Expenses'!$B$8:$B$500,">="&B42,'💸 Expenses'!$B$8:$B$500,"<"&(B42+1)) | I42: =IFERROR(F42-H42,0) | J42: =IFERROR(I42/F42,0) | L42: Cierre via loka.py | R42: =IFERROR(D42*$T$7,0)
B43: 46195 | C43: Mon | D43: 2459 | E43: 1800 | F43: =IFERROR(D43+E43+G43,0) | G43: 0 | H43: =SUMIFS('💸 Expenses'!$F$8:$F$500,'💸 Expenses'!$B$8:$B$500,">="&B43,'💸 Expenses'!$B$8:$B$500,"<"&(B43+1)) | I43: =IFERROR(F43-H43,0) | J43: =IFERROR(I43/F43,0) | L43: Cierre via loka.py | R43: =IFERROR(D43*$T$7,0)
... B52: 46204 | C52: Wed | D52: 2498 | E52: 2024 | F52: =IFERROR(D52+E52+G52,0) | G52: 0 | H52: =SUMIFS('💸 Expenses'!$F$8:$F$500,'💸 Expenses'!$B$8:$B$500,">="&B52,'💸 Expenses'!$B$8:$B$500,"<"&(B52+1)) | I52: =IFERROR(F52-H52,0) | J52: =IFERROR(I52/F52,0) | L52: Cierre via loka.py | R52: =IFERROR(D52*$T$7,0)
B53: 46205 | C53: Thu | D53: 1859 | E53: 1249 | F53: =IFERROR(D53+E53+G53,0) | G53: 0 | H53: =SUMIFS('💸 Expenses'!$F$8:$F$500,'💸 Expenses'!$B$8:$B$500,">="&B53,'💸 Expenses'!$B$8:$B$500,"<"&(B53+1)) | I53: =IFERROR(F53-H53,0) | J53: =IFERROR(I53/F53,0) | K53: incl +$120 additional card income (added 02-Jul) | L53: Cierre via loka.py | R53: =IFERROR(D53*$T$7,0)
B54: 46206 | C54: Fri | D54: 3702 | E54: 2375 | F54: =IFERROR(D54+E54+G54,0) | G54: 0 | H54: =SUMIFS('💸 Expenses'!$F$8:$F$500,'💸 Expenses'!$B$8:$B$500,">="&B54,'💸 Expenses'!$B$8:$B$500,"<"&(B54+1)) | I54: =IFERROR(F54-H54,0) | J54: =IFERROR(I54/F54,0) | K54: incl +$110 additional cash income (added 04-Jul) | L54: Cierre via loka.py | R54: =IFERROR(D54*$T$7,0)
B55: 46207 | C55: Sat | D55: 1739 | E55: 895 | F55: =IFERROR(D55+E55+G55,0) | G55: 0 | H55: =SUMIFS('💸 Expenses'!$F$8:$F$500,'💸 Expenses'!$B$8:$B$500,">="&B55,'💸 Expenses'!$B$8:$B$500,"<"&(B55+1)) | I55: =IFERROR(F55-H55,0) | J55: =IFERROR(I55/F55,0) | L55: Cierre via loka.py | R55: =IFERROR(D55*$T$7,0)
B56: 46209 | C56: Mon | D56: 2190 | E56: 1500 | F56: =IFERROR(D56+E56+G56,0) | G56: 0 | H56: =SUMIFS('💸 Expenses'!$F$8:$F$500,'💸 Expenses'!$B$8:$B$500,">="&B56,'💸 Expenses'!$B$8:$B$500,"<"&(B56+1)) | I56: =IFERROR(F56-H56,0) | J56: =IFERROR(I56/F56,0) | L56: Cierre via loka.py | R56: =IFERROR(D56*$T$7,0)
B57: 46210 | C57: Tue | D57: 1840 | E57: 1820 | F57: =IFERROR(D57+E57+G57,0) | G57: 0 | H57: =SUMIFS('💸 Expenses'!$F$8:$F$500,'💸 Expenses'!$B$8:$B$500,">="&B57,'💸 Expenses'!$B$8:$B$500,"<"&(B57+1)) | I57: =IFERROR(F57-H57,0) | J57: =IFERROR(I57/F57,0) | L57: Cierre via loka.py | R57: =IFERROR(D57*$T$7,0)
B58: 46211 | C58: Wed | D58: 360 | E58: 2055 | F58: =IFERROR(D58+E58+G58+U58,0) | G58: 195 | H58: =SUMIFS('💸 Expenses'!$F$8:$F$500,'💸 Expenses'!$B$8:$B$500,">="&B58,'💸 Expenses'!$B$8:$B$500,"<"&(B58+1)) | I58: =IFERROR(F58-H58,0) | J58: =IFERROR(I58/F58,0) | L58: EOD close (dual card: MP + Soft Restaurant) | R58: =IFERROR(D58*$T$7,0) | U58: 1078 | V58: 22.1
B59: 46212 | C59: Thu | D59: 1940 | E59: 3685 | F59: =IFERROR(D59+E59+G59+U59,0) | G59: 120 | H59: =SUMIFS('💸 Expenses'!$F$8:$F$500,'💸 Expenses'!$B$8:$B$500,">="&B59,'💸 Expenses'!$B$8:$B$500,"<"&(B59+1)) | I59: =IFERROR(F59-H59,0) | J59: =IFERROR(I59/F59,0) | L59: EOD close (dual card: MP + Soft Restaurant, actual comm) | R59: =IFERROR(D59*$T$7,0) | U59: 270 | V59: 5.01
B60: 46213 | C60: Fri | D60: 1700 | E60: 1730 | F60: =IFERROR(D60+E60+G60+U60,0) | G60: 70 | H60: =SUMIFS('💸 Expenses'!$F$8:$F$500,'💸 Expenses'!$B$8:$B$500,">="&B60,'💸 Expenses'!$B$8:$B$500,"<"&(B60+1)) | I60: =IFERROR(F60-H60,0) | J60: =IFERROR(I60/F60,0) | L60: EOD close (MP only; no Soft card today) | R60: =IFERROR(D60*$T$7,0) | U60: 0 | V60: 0
B61: 46214 | C61: Sat | D61: 280 | E61: 1235 | F61: =IFERROR(D61+E61+G61+U61,0) | G61: 0 | H61: =SUMIFS('💸 Expenses'!$F$8:$F$500,'💸 Expenses'!$B$8:$B$500,">="&B61,'💸 Expenses'!$B$8:$B$500,"<"&(B61+1)) | I61: =IFERROR(F61-H61,0) | J61: =IFERROR(I61/F61,0) | L61: EOD close (dual card: MP + Soft Restaurant) | R61: =IFERROR(D61*$T$7,0) | U61: 1210 | V61: 26.03

Sheet 💸 Expenses
A2: 💸 LOKA — EXPENSES TRACKER | E2: Log every cost: ingredients, staff, utilities, supplies…
B5: TODAY | C5: THIS WEEK | D5: THIS MONTH | E5: INGREDIENTS | F5: STAFF | G5: UTILITIES | H5: TODAY TOTAL | I5: WEEK TOTAL
B6: =SUMIFS($F$8:$F$500,$B$8:$B$500,TODAY()) | C6: =SUMIFS($F$8:$F$500,$B$8:$B$500,">="&(TODAY()-WEEKDAY(TODAY(),2)+1),$B$8:$B$500,"<="&(TODAY()-WEEKDAY(TODAY(),2)+7)) | D6: =SUMIFS($F$8:$F$500,$B$8:$B$500,">="&DATE(YEAR(TODAY()),MONTH(TODAY()),1),$B$8:$B$500,"<"&DATE(YEAR(TODAY()),MONTH(TODAY())+1,1)) | E6: =SUMIF($E$8:$E$500,"Ingredients*",$F$8:$F$500) | F6: =SUMIF($E$8:$E$500,"Staff*",$F$8:$F$500) | G6: =SUMIF($E$8:$E$500,"Supplies*",$F$8:$F$500)+SUMIF($E$8:$E$500,"Utilities*",$F$8:$F$500) | H6: =SUMIFS($F$8:$F$500,$B$8:$B$500,TODAY()) | I6: =SUMIFS($F$8:$F$500,$B$8:$B$500,">="&(TODAY()-WEEKDAY(TODAY(),2)+1),$B$8:$B$500,"<="&(TODAY()-WEEKDAY(TODAY(),2)+7))
B7: Date | C7: Description | D7: Supplier | E7: Category | F7: Amount ($) | G7: Paid By | H7: Payment Method | I7: Status | J7: Notes
B8: 46160 | C8: Carne | D8: — | E8: Ingredients - Meat | F8: 420 | G8: Restaurant | H8: Cash | I8: ✅ Paid
B9: 46160 | C9: Basicos | D9: — | E9: Ingredients - Pantry | F9: 1068 | G9: Restaurant | H9: Cash | I9: ✅ Paid
B10: 46160 | C10: Real Pan Services | D10: Real Pan | E10: Ingredients - Bread | F10: 522 | G10: Restaurant | H10: Cash | I10: ✅ Paid
B11: 46160 | C11: Chedruai | D11: Chedraui | E11: Supermarket / General | F11: 129 | G11: Restaurant | H11: Cash | I11: ✅ Paid
B12: 46160 | C12: Vegetables | D12: Abastos | E12: Ingredients - Vegetables | F12: 400 | G12: Restaurant | H12: Cash | I12: ✅ Paid
B13: 46160 | C13: Vegetables | D13: — | E13: Ingredients - Vegetables | F13: 90 | G13: Restaurant | H13: Cash | I13: ✅ Paid
B14: 46161 | C14: Arroz | D14: — | E14: Ingredients - Pantry | F14: 30 | G14: Restaurant | H14: Cash | I14: ✅ Paid
B15: 46162 | C15: Lechuga | D15: — | E15: Ingredients - Vegetables | F15: 65 | G15: Restaurant | H15: Cash | I15: ✅ Paid
B16: 46162 | C16: Tortillas | D16: — | E16: Ingredients - Pantry | F16: 26 | G16: Restaurant | H16: Cash | I16: ✅ Paid
B17: 46162 | C17: Jamon Mexicana | D17: — | E17: Ingredients - Meat | F17: 88 | G17: Restaurant | H17: Cash | I17: ✅ Paid
B18: 46162 | C18: Carne | D18: — | E18: Ingredients - Meat | F18: 1104 | G18: Restaurant | H18: Cash | I18: ✅ Paid
B19: 46162 | C19: Salmon | D19: — | E19: Ingredients - Meat & Fish | F19: 397 | G19: Restaurant | H19: Cash | I19: ✅ Paid
... B46: 46165 | C46: Agua Natural | D46: — | E46: Supplies / Other | F46: 30 | G46: Restaurant | H46: Cash | I46: ✅ Paid
B47: 46165 | C47: John - Saldo Semana | D47: Nomina | E47: Staff - Salary | F47: 3250 | G47: Restaurant | H47: Cash | I47: ✅ Paid | J47: Head Chef — weekly salary Week 1
B48: 46165 | C48: Debi - Limpieza | D48: Nomina | E48: Staff - Salary | F48: 1500 | G48: Restaurant | H48: Cash | I48: ✅ Paid | J48: Cleaning staff — weekly salary Week 1
B49: 46165 | C49: Victor - Mesero (2 dias) | D49: Nomina | E49: Staff - Salary | F49: 666 | G49: Restaurant | H49: Cash | I49: ✅ Paid | J49: Waiter — 2 days salary Week 1
B50: 46165 | C50: Sal Fina (20 x 1 kg) | D50: Costco | E50: Ingredients - Pantry | F50: 408.17 | G50: Restaurant | H50: Card | I50: ✅ Paid | J50: Costco — Sal Fina 20/1KG
B51: 46165 | C51: Coca Cola (24 x 600ml) | D51: Costco | E51: Ingredients - Beverages | F51: 455.23 | G51: Restaurant | H51: Card | I51: ✅ Paid | J51: Costco — discount applied, total $844
B52: 46165 | C52: Leche Deslactosada (12 x 1LT) | D52: Sam's Club | E52: Ingredients - Dairy | F52: 317.13 | G52: Restaurant | H52: Card | I52: ✅ Paid | J52: Sam's Club — reimbursed to Shashirekha, settled
B53: 46165 | C53: Leche Alpura (12 x 1L) | D53: Sam's Club | E53: Ingredients - Dairy | F53: 317.13 | G53: Restaurant | H53: Card | I53: ✅ Paid | J53: Sam's Club — reimbursed to Shashirekha, settled
B54: 46165 | C54: Crema Ácida | D54: Sam's Club | E54: Ingredients - Dairy | F54: 250.63 | G54: Restaurant | H54: Card | I54: ✅ Paid | J54: Sam's Club — reimbursed to Shashirekha, settled
B55: 46165 | C55: Salsa / Tomate (12 x 600ml) | D55: Sam's Club | E55: Ingredients - Pantry | F55: 232.22 | G55: Restaurant | H55: Card | I55: ✅ Paid | J55: Sam's Club — reimbursed to Shashirekha, settled
B56: 46165 | C56: Champiñones (24 x 400ml) | D56: Sam's Club | E56: Ingredients - Vegetables | F56: 218.92 | G56: Restaurant | H56: Card | I56: ✅ Paid | J56: Sam's Club — reimbursed to Shashirekha, settled
B57: 46166 | C57: Guayabas Mediana | D57: Aviles Hernandez | E57: Ingredients - Fruit | F57: 120 | G57: Restaurant | H57: Cash | I57: ✅ Paid
B58: 46166 | C58: Jicamas + Pinas + Melon Chino | D58: El Matamoros | E58: Ingredients - Fruit | F58: 147 | G58: Restaurant | H58: Cash | I58: ✅ Paid
B59: 46166 | C59: Cilantro + Italiana | D59: Oscar Verduras | E59: Ingredients - Vegetables | F59: 100 | G59: Restaurant | H59: Cash | I59: ✅ Paid
B60: 46166 | C60: Habanero + Pepino | D60: Remision Formitec | E60: Ingredients - Vegetables | F60: 90 | G60: Restaurant | H60: Cash | I60: ✅ Paid
B61: 46166 | C61: Betabel (~1.9 kg) | D61: Nota Remision | E61: Ingredients - Vegetables | F61: 78 | G61: Restaurant | H61: Cash | I61: ✅ Paid
B62: 46166 | C62: Jitomate | D62: Brisia y Hermanos | E62: Ingredients - Vegetables | F62: 178 | G62: Restaurant | H62: Cash | I62: ✅ Paid
B63: 46166 | C63: Mango + Sandia | D63: Papayas Maradol | E63: Ingredients - Fruit | F63: 116 | G63: Restaurant | H63: Cash | I63: ✅ Paid
B64: 46166 | C64: Verduras variadas | D64: JP Verduras | E64: Ingredients - Vegetables | F64: 224 | G64: Restaurant | H64: Cash | I64: ✅ Paid
B65: 46166 | C65: Pimiento Morron | D65: Sin factura | E65: Ingredients - Vegetables | F65: 23 | G65: Restaurant | H65: Cash | I65: ✅ Paid | J65: No receipt — Sin factura
B66: 46167 | C66: Pan para Hamburguesa con Ajonjolí + Pan de Caja Arandano | D66: Real Abastos | E66: Ingredients - Bread | F66: 273 | G66: Restaurant | H66: Card | I66: ✅ Paid | J66: Real Sucursal Central de Abastos — 12 pcs hamburger buns + 3x900g bread
B67: 46167 | C67: Limonada / Naranjada / Tamarindo 1LT (18 pcs) | D67: Reca del Bajio | E67: Ingredients - Beverages | F67: 450 | G67: Restaurant | H67: Card | I67: ✅ Paid | J67: Mercado Pago — 6 Limonada + 6 Naranjada + 6 Tamarindo
B68: 46167 | C68: QsoCrema Lala 190g | D68: Chedraui Selecto | E68: Ingredients - Dairy | F68: 32 | G68: Restaurant | H68: Card | I68: ✅ Paid
B69: 46167 | C69: Tortillas Blanca (2.21 kg) | D69: Chedraui Selecto | E69: Ingredients - Pantry | F69: 28.73 | G69: Restaurant | H69: Card | I69: ✅ Paid
B70: 46167 | C70: Rosca de Nuez | D70: Chedraui Selecto | E70: Ingredients - Bread | F70: 89 | G70: Restaurant | H70: Card | I70: ✅ Paid
B71: 46167 | C71: Bolillo (6 pcs) | D71: Chedraui Selecto | E71: Ingredients - Bread | F71: 12.6 | G71: Restaurant | H71: Card | I71: ✅ Paid
B72: 46167 | C72: Salmon lonja (1.455 kg) | D72: Brisa del Mar | E72: Ingredients - Meat & Fish | F72: 494.7 | G72: Restaurant | H72: Cash | I72: ✅ Paid | J72: 1.455 kg x $340/kg
B73: 46167 | C73: Papas (4 bolsas) | D73: — | E73: Ingredients - Vegetables | F73: 440 | G73: Restaurant | H73: Cash | I73: ✅ Paid | J73: Remision handwritten
B74: 46167 | C74: Costillas cerdo | D74: — | E74: Ingredients - Meat | F74: 282 | G74: Restaurant | H74: Cash | I74: ✅ Paid | J74: Remision handwritten
B75: 46167 | C75: Azucar Est Posada 1K | D75: OXXO | E75: Ingredients - Pantry | F75: 25 | G75: Restaurant | H75: Card | I75: ✅ Paid | J75: Paid via Mercado Libre
B76: 46167 | C76: Pollo NutryEnt (4 packs, 8.29 kg) | D76: Chedraui Paseo | E76: Ingredients - Meat | F76: 323.36 | G76: Restaurant | H76: Card | I76: ✅ Paid | J76: 4 x PolloNutryEnt ~2kg each
B77: 46167 | C77: Naranja de Jugo (1.265 kg) | D77: Chedraui Paseo | E77: Ingredients - Fruit | F77: 37.82 | G77: Restaurant | H77: Card | I77: ✅ Paid
B78: 46167 | C78: Mango Paraiso (1.560 kg) | D78: Chedraui Paseo | E78: Ingredients - Fruit | F78: 45.24 | G78: Restaurant | H78: Card | I78: ✅ Paid
B79: 46167 | C79: Azucar Ref 10/1K + Pastel Chocolate | D79: Costco | E79: Ingredients - Pantry | F79: 488 | G79: Restaurant | H79: Card | I79: ✅ Paid | J79: Azucar $275.18 + Pastel $224.03 — discount $11.21 applied
B80: 46168 | C80: Arroz Extra LP 500G | D80: OXXO | E80: Ingredients - Pantry | F80: 47.6 | G80: Restaurant | H80: Card | I80: ✅ Paid | J80: OXXO Circunvalacion QRF
B81: 46168 | C81: Chapata Grande Sabores Varios (24) | D81: Real Abastos | E81: Ingredients - Bread | F81: 288 | G81: Restaurant | H81: Card | I81: ✅ Paid | J81: 24 pcs x $12 = $288
B82: 46168 | C82: Tilapia (~6.74 kg) | D82: Pescaderia El Faro | E82: Ingredients - Meat & Fish | F82: 244 | G82: Restaurant | H82: Cash | I82: ✅ Paid | J82: Nota El Faro — corrected from $944 to $244
B83: 46168 | C83: Bistek de Puerco | D83: Remision | E83: Ingredients - Meat | F83: 586 | G83: Restaurant | H83: Card | I83: ✅ Paid | J83: Remision + Getnet card terminal
B84: 46168 | C84: Tortillas Blancos | D84: — | E84: Ingredients - Pantry | F84: 26 | G84: Restaurant | H84: Cash | I84: ✅ Paid | J84: No bill — cash purchase
B85: 46169 | C85: Jamon Delicia Pierna Mandolin (2.005 kg) | D85: San Juan Salchichonerias | E85: Ingredients - Meat | F85: 170.22 | G85: Restaurant | H85: Card | I85: ✅ Paid | J85: Rappi delivery — 27 May
B86: 46169 | C86: Arroz La Posada 900g (x3, 2x1 promo) | D86: OXXO | E86: Ingredients - Pantry | F86: 60 | G86: Restaurant | H86: Card | I86: ✅ Paid | J86: OXXO Unity QRF — buy 2 get 1 promo
B87: 46169 | C87: Tres Leches Frutos Rojos | D87: Lecaroz 1972 | E87: Ingredients - Desserts | F87: 260 | G87: Restaurant | H87: Card | I87: ✅ Paid | J87: Panadería Circunvalacion
B88: 46169 | C88: Tocino | D88: Remision | E88: Ingredients - Meat | F88: 236 | G88: Restaurant | H88: Card | I88: ✅ Paid | J88: Remision + Getnet card terminal
B89: 46169 | C89: Tortillas Blancos | D89: — | E89: Ingredients - Pantry | F89: 52 | G89: Restaurant | H89: Cash | I89: ✅ Paid | J89: No bill — cash purchase
B90: 46169 | C90: Vegetables | D90: — | E90: Ingredients - Vegetables | F90: 295 | G90: Restaurant | H90: Cash | I90: ✅ Paid | J90: No bill — cash purchase
... B92: 46170 | C92: Muslo c/Hueso Amarillo + Elote + Cebolla | D92: H-E-B | E92: Ingredients - Meat | F92: 83.91 | G92: Restaurant | H92: Card | I92: ✅ Paid | J92: Net after return of $268.91 (chicken issue)
B93: 46170 | C93: QsoCrema Lala + Tortilla Amarilla | D93: Chedraui Selecto | E93: Ingredients - Dairy | F93: 56.11 | G93: Restaurant | H93: Card | I93: ✅ Paid
B94: 46170 | C94: Microfibra Formula (2 pcs) | D94: Chedraui Selecto | E94: Supplies / Other | F94: 23.2 | G94: Restaurant | H94: Card | I94: ✅ Paid | J94: Cleaning supplies
B95: 46170 | C95: Nutralat Milk 1.5L (x2) | D95: OXXO | E95: Ingredients - Dairy | F95: 48 | G95: Restaurant | H95: Card | I95: ✅ Paid | J95: OXXO Pathe QRF
B96: 46170 | C96: Muslo con Hueso (4.8 kg) | D96: Merjaliz | E96: Ingredients - Meat | F96: 336 | G96: Restaurant | H96: Cash | I96: ✅ Paid | J96: Mercado de Abastos — 4.8kg x $70
B97: 46170 | C97: Queso Panela Quinta Azul Granel (2.4 kg) | D97: CAQ | E97: Ingredients - Dairy | F97: 296.12 | G97: Restaurant | H97: Card | I97: ✅ Paid | J97: 2.4kg x $123.38
B98: 46170 | C98: Queso Gouda Menona (1 unit) | D98: Bodega del Queso | E98: Ingredients - Dairy | F98: 135 | G98: Restaurant | H98: Cash | I98: ✅ Paid | J98: Restaurant portion only — 1 of 2 units
B99: 46170 | C99: Lechuga Italiana | D99: — | E99: Ingredients - Vegetables | F99: 48 | G99: Restaurant | H99: Cash | I99: ✅ Paid | J99: No bill
B100: 46170 | C100: Hielo | D100: — | E100: Supplies / Other | F100: 100 | G100: Restaurant | H100: Cash | I100: ✅ Paid | J100: No bill
B101: 46170 | C101: Agua Natural | D101: — | E101: Supplies / Other | F101: 45 | G101: Restaurant | H101: Cash | I101: ✅ Paid | J101: No bill
B102: 46170 | C102: Potato (Papas) | D102: — | E102: Ingredients - Vegetables | F102: 200 | G102: Restaurant | H102: Cash | I102: ✅ Paid | J102: No bill
B103: 46170 | C103: Lechuga Italiana | D103: — | E103: Ingredients - Vegetables | F103: 30 | G103: Restaurant | H103: Cash | I103: ✅ Paid | J103: No bill
B104: 46171 | C104: Jitomate (2.030 kg) | D104: Super Fruterias Bermudez | E104: Ingredients - Vegetables | F104: 99.47 | G104: Restaurant | H104: Cash | I104: ✅ Paid | J104: 2.030kg x $49/kg
B105: 46171 | C105: Tortillas Blanca (3.875 kg) | D105: Chedraui Paseo | E105: Ingredients - Pantry | F105: 51.92 | G105: Restaurant | H105: Card | I105: ✅ Paid
B106: 46171 | C106: Concha Chocolate (3 pcs) | D106: Chedraui Paseo | E106: Ingredients - Bread | F106: 36 | G106: Restaurant | H106: Card | I106: ✅ Paid
B107: 46171 | C107: Rosca Marmoleada | D107: Chedraui Paseo | E107: Ingredients - Bread | F107: 69.9 | G107: Restaurant | H107: Card | I107: ✅ Paid
B108: 46172 | C108: Arroz La Posada 900g (4 pcs, 2x1 promo) | D108: OXXO Pathe QRF | E108: Ingredients - Pantry | F108: 60 | G108: Restaurant | H108: Card | I108: ✅ Paid | J108: 4 packs, buy 2 get 2 promo — $11.60 saving
B109: 46172 | C109: Frijol Bayos REF 430g | D109: OXXO Pathe QRF | E109: Ingredients - Pantry | F109: 17.9 | G109: Restaurant | H109: Card | I109: ✅ Paid | J109: $1.00 discount applied
B110: 46172 | C110: Huevo BCO Bachoco 12P | D110: OXXO Pathe QRF | E110: Ingredients - Pantry | F110: 36 | G110: Restaurant | H110: Cash | I110: ✅ Paid | J110: $8.50 discount applied — paid $50 cash change $14
B111: 46172 | C111: Frutas y Verduras variadas | D111: Fruteria Franco | E111: Ingredients - Fruit | F111: 220 | G111: Restaurant | H111: Card | I111: ✅ Paid | J111: Mercado Pago — Fruteria Franco
B112: 46172 | C112: Pollo Muslo | D112: — | E112: Ingredients - Meat | F112: 310 | G112: Restaurant | H112: Cash | I112: ✅ Paid | J112: No bill — cash purchase
B113: 46172 | C113: John — Saldo Semana (Week 2) | D113: Nomina | E113: Staff - Salary | F113: 3750 | G113: Restaurant | H113: Cash | I113: ✅ Paid | J113: Head Chef — weekly salary Week 2
B114: 46172 | C114: Duvi/Debi — Limpieza (Week 2) | D114: Nomina | E114: Staff - Salary | F114: 1500 | G114: Restaurant | H114: Cash | I114: ✅ Paid | J114: Cleaning staff — weekly salary Week 2
B115: 46172 | C115: Tomate (0.930 kg) | D115: Super Fruterias Bermudez | E115: Ingredients - Vegetables | F115: 18.6 | G115: Restaurant | H115: Cash | I115: ✅ Paid | J115: 0.930kg x $20/kg
B116: 46172 | C116: Jitomate (1.180 kg) | D116: Super Fruterias Bermudez | E116: Ingredients - Vegetables | F116: 57.8 | G116: Restaurant | H116: Cash | I116: ✅ Paid | J116: 1.180kg x $49/kg
B117: 46172 | C117: Cilantro (4 un) | D117: Super Fruterias Bermudez | E117: Ingredients - Vegetables | F117: 4 | G117: Restaurant | H117: Cash | I117: ✅ Paid | J117: 4 units x $1/un
B118: 46173 | C118: Aceite La Posada 800 (12 units, 2x1 promo) | D118: OXXO | E118: Ingredients - Pantry | F118: 312 | G118: Restaurant | H118: Card | I118: ✅ Paid | J118: $70.80 discount applied — Mercado Libre payment
B119: 46174 | C119: Azucar Morena 10/1 | D119: Costco | E119: Ingredients - Pantry | F119: 219.94 | G119: Restaurant | H119: Card | I119: ✅ Paid
B120: 46174 | C120: Atun DOL.AG 10/140 | D120: Costco | E120: Ingredients - Pantry | F120: 193.34 | G120: Restaurant | H120: Card | I120: ✅ Paid
B121: 46174 | C121: Mayonesa 3.7L (x2) | D121: Costco | E121: Ingredients - Pantry | F121: 468.52 | G121: Restaurant | H121: Card | I121: ✅ Paid | J121: 2 packs x $234.26
B122: 46174 | C122: Agua Mineral 12/600ml | D122: Costco | E122: Ingredients - Beverages | F122: 230.16 | G122: Restaurant | H122: Card | I122: ✅ Paid | J122: Net after $30.68 discount split
B123: 46174 | C123: Pastel Queso Guayaba | D123: Costco | E123: Ingredients - Bread | F123: 224.04 | G123: Restaurant | H123: Card | I123: ✅ Paid | J123: Net after discount allocation
B124: 46174 | C124: Arroz 10/900 (3 packs) | D124: Sam's Club | E124: Ingredients - Pantry | F124: 540 | G124: Restaurant | H124: Card | I124: ✅ Paid | J124: 3 x $184.14, discount -$12.42
B125: 46174 | C125: Arrachera Clarita | D125: Miscelanea LC La Cruz | E125: Ingredients - Meat | F125: 303 | G125: Restaurant | H125: Card | I125: ✅ Paid | J125: Getnet terminal
B126: 46174 | C126: Bistec Res | D126: Miscelanea LC La Cruz | E126: Ingredients - Meat | F126: 260 | G126: Restaurant | H126: Card | I126: ✅ Paid
B127: 46174 | C127: Bistec CD | D127: Miscelanea LC La Cruz | E127: Ingredients - Meat | F127: 293 | G127: Restaurant | H127: Card | I127: ✅ Paid
B128: 46174 | C128: DeoCrema Lala 190g (x2) | D128: Chedraui Selecto | E128: Ingredients - Dairy | F128: 64 | G128: Restaurant | H128: Card | I128: ✅ Paid
B129: 46174 | C129: Tortillas Blanca K (5.4 kg) | D129: Chedraui Selecto | E129: Ingredients - Pantry | F129: 67.5 | G129: Restaurant | H129: Card | I129: ✅ Paid | J129: 3.446kg+1.955kg net after discount
B130: 46174 | C130: Rosca de Nuez | D130: Chedraui Selecto | E130: Ingredients - Bread | F130: 79.9 | G130: Restaurant | H130: Card | I130: ✅ Paid
...

Sheet 📦 Inventory
A2: 📦 LOKA — INVENTORY | F2: Update stock levels when you receive deliveries or do stock checks
B5: TOTAL ITEMS | D5: ⚠️ LOW STOCK | E5: LOW STOCK # | F5: 🚫 OUT OF STOCK | H5: ALERT COUNT | J5: LAST UPDATED
B6: =COUNTA(B9:B200) | D6: =COUNTIF(J9:J200,"⚠️ LOW STOCK") | E6: =COUNTIF(J9:J200,"⚠️ LOW STOCK")+COUNTIF(J9:J200,"🚫 OUT OF STOCK") | F6: =COUNTIF(J9:J200,"🚫 OUT OF STOCK") | H6: =COUNTIF(J9:J200,"⚠️ LOW STOCK")+COUNTIF(J9:J200,"🚫 OUT OF STOCK") | J6: =TODAY()
B8: Item Name | Category | Unit | Min Stock | Current Stock | Last Ordered | Supplier | Status | Notes
B9: Carne de Res | C9: Ingredients - Meat | D9: kg | E9: 0 | J9: =IF(ISBLANK(F9),"—",IF(F9=0,"🚫 OUT OF STOCK",IF(F9<=E9,"⚠️ LOW STOCK","✅ OK")))
B10: Jamon Mexicano | C10: Ingredients - Meat | D10: kg | E10: 0 | J10: =IF(ISBLANK(F10),"—",IF(F10=0,"🚫 OUT OF STOCK",IF(F10<=E10,"⚠️ LOW STOCK","✅ OK")))
B11: Pollo | C11: Ingredients - Meat | D11: kg | E11: 0 | J11: =IF(ISBLANK(F11),"—",IF(F11=0,"🚫 OUT OF STOCK",IF(F11<=E11,"⚠️ LOW STOCK","✅ OK")))
B12: Chuletas de Carne | C12: Ingredients - Meat | D12: kg | E12: 0 | J12: =IF(ISBLANK(F12),"—",IF(F12=0,"🚫 OUT OF STOCK",IF(F12<=E12,"⚠️ LOW STOCK","✅ OK")))
B13: Costillas de Cerdo | C13: Ingredients - Meat | D13: kg | E13: 0 | J13: =IF(ISBLANK(F13),"—",IF(F13=0,"🚫 OUT OF STOCK",IF(F13<=E13,"⚠️ LOW STOCK","✅ OK")))
B14: Salmon | C14: Ingredients - Meat & Fish | D14: kg | E14: 0 | J14: =IF(ISBLANK(F14),"—",IF(F14=0,"🚫 OUT OF STOCK",IF(F14<=E14,"⚠️ LOW STOCK","✅ OK")))
B15: Filete de Mojarra | C15: Ingredients - Meat & Fish | D15: kg | E15: 0 | J15: =IF(ISBLANK(F15),"—",IF(F15=0,"🚫 OUT OF STOCK",IF(F15<=E15,"⚠️ LOW STOCK","✅ OK")))
B16: Papas | C16: Ingredients - Vegetables | D16: kg | E16: 0 | J16: =IF(ISBLANK(F16),"—",IF(F16=0,"🚫 OUT OF STOCK",IF(F16<=E16,"⚠️ LOW STOCK","✅ OK")))
B17: Lechuga | C17: Ingredients - Vegetables | D17: pcs | E17: 0 | J17: =IF(ISBLANK(F17),"—",IF(F17=0,"🚫 OUT OF STOCK",IF(F17<=E17,"⚠️ LOW STOCK","✅ OK")))
B18: Jitomate | C18: Ingredients - Vegetables | D18: kg | E18: 0 | J18: =IF(ISBLANK(F18),"—",IF(F18=0,"🚫 OUT OF STOCK",IF(F18<=E18,"⚠️ LOW STOCK","✅ OK")))
B19: Cilantro | C19: Ingredients - Vegetables | D19: pcs | E19: 0 | J19: =IF(ISBLANK(F19),"—",IF(F19=0,"🚫 OUT OF STOCK",IF(F19<=E19,"⚠️ LOW STOCK","✅ OK")))
B20: Italiana | C20: Ingredients - Vegetables | D20: pcs | E20: 0 | J20: =IF(ISBLANK(F20),"—",IF(F20=0,"🚫 OUT OF STOCK",IF(F20<=E20,"⚠️ LOW STOCK","✅ OK")))
... B73: Huevo Bachoco | C73: Ingredients - Pantry | D73: pcs | E73: 0 | J73: =IF(ISBLANK(F73),"—",IF(F73=0,"🚫 OUT OF STOCK",IF(F73<=E73,"⚠️ LOW STOCK","✅ OK")))

Sheet 👥 Staff & Payroll
A2: 👥 LOKA — STAFF & PAYROLL | D2: Weekly schedule + auto payroll calculation
A6: STAFF SCHEDULE — Week of: | D6: =TODAY()-WEEKDAY(TODAY(),2)+1
A7: Staff Name | B7: Role | C7: Daily Rate ($) | D7: Mon | E7: Tue | F7: Wed | G7: Thu | H7: Fri | I7: Sat | J7: Sun | K7: Days Worked | L7: Week Pay ($)
A8: John | B8: Head Chef | C8: 625 | D8: Full Day | E8: Full Day | F8: Full Day | G8: Full Day | H8: Full Day | I8: Full Day | J8: Day Off | K8: =COUNTIF(D8:J8,"Full Day") | L8: =K8*C8
A9: Debi | B9: Cleaner | C9: 250 | D9: Full Day | E9: Full Day | F9: Full Day | G9: Full Day | H9: Full Day | I9: Full Day | J9: Day Off | K9: =COUNTIF(D9:J9,"Full Day") | L9: =K9*C9
A10: Victor (INACTIVE) | B10: Mesero — Left after Week 1 | C10: 0 | D10: — | E10: — | F10: — | G10: — | H10: — | I10: — | J10: — | K10: 0 | L10: 0
A11: Judith (RESIGNED) | B11: Mesera — Resigned 7 Jun · paid in full 8 Jun | C11: 0 | D11: — | E11: — | F11: — | G11: — | H11: — | I11: — | J11: — | K11: 0 | L11: 0
A12: Cesar (RESIGNED) | B12: Mesero — Started Tue 9 Jun · Resigned · Week 4 paid in full (5 days) | C12: 0 | D12: — | E12: — | F12: — | G12: — | H12: — | I12: — | J12: — | K12: 0 | L12: 0
A13: Samu | B13: Ayudante / Support | C13: 160 | D13: Full Day | E13: Full Day | F13: Full Day | G13: Full Day | H13: Full Day | I13: Day Off | J13: Day Off | K13: =COUNTIF(D13:J13,"Full Day") | L13: =K13*C13
A20: MONTHLY PAYROLL PROJECTION
A21: Staff Name | B21: Role | C21: Week Pay ($) | D21: x Weeks/Month | E21: Monthly ($) | F21: IMSS / Benefits % | G21: Total Monthly Cost ($) | H21: Notes
A22: =A8 | B22: Head Chef | C22: =L8 | D22: 4 | E22: =C22*D22 | F22: 0.08 | G22: =E22*(1+F22)
A23: =A9 | B23: Cleaner / Limpieza | C23: =L9 | D23: 4 | E23: =C23*D23 | F23: 0.08 | G23: =E23*(1+F23)
A24: =A10 | B24: Mesero (left Wk1) | C24: =L10 | D24: 4 | E24: =C24*D24 | F24: 0.08 | G24: =E24*(1+F24)
A25: =A11 | B25: Mesera (resigned) | C25: =L11 | D25: 4 | E25: =C25*D25 | F25: 0.08 | G25: =E25*(1+F25)
A26: =A12 | B26: Mesero / Waiter | C26: =L12 | D26: 4 | E26: =C26*D26 | F26: 0.08 | G26: =E26*(1+F26)
A27: =A13 | B27: Ayudante / Support | C27: =L13 | D27: 4 | E27: =C27*D27 | F27: 0.08 | G27: =E27*(1+F27)
A28: =A14 | B28: Kitchen Helper | C28: =L14 | D28: 4 | E28: =C28*D28 | F28: 0.08 | G28: =E28*(1+F28)
A29: =A15 | E29: =C29*D29 | G29: =E29*(1+F29)
A30: TOTAL MONTHLY PAYROLL COST | G30: =SUM(G21:G28)
A33: ── WEEKLY FIXED COSTS & BREAK-EVEN TARGETS ──
A34: COST ITEM | B34: WEEKLY ($) | C34: MONTHLY EST. ($) | D34: NOTES
A35: John — Head Chef Salary | B35: 3750 | C35: 15000 | D35: Confirmed weekly rate
A36: Debi — Limpieza Salary | B36: 1500 | C36: 6000 | D36: Confirmed weekly rate
A37: Cesar — Mesero Salary (RESIGNED) | B37: 0 | C37: 0 | D37: Resigned — Week 4 paid in full · removed from forward fixed costs
A38: Samu — Ayudante Salary | B38: 800 | C38: 3200 | D38: Confirmed — $800/week | $160/day | 5 days Mon–Fri | Start 9 Jun 2026
A39: Rent + Maintenance (actual — $20,000/mo) | B39: 5000 | C39: 20000 | D39: Confirmed — $20,000/month actual
A40: Utilities — Electricity + Gas (estimated) | B40: 1000 | C40: 4000 | D40: ⏳ Approx — bills pending · electricity + gas
A41: TOTAL FIXED COSTS (current) | B41: =SUM(B35:B40) | C41: =SUM(C35:C40) | D41: Incl. rent + maintenance + utilities est.
A43: ── MESERO STATUS — ✅ CESAR + SAMU ACTIVE FROM 9 JUN 2026 ──
A44: Judith — Mesera Salary (historical — resigned 7 Jun) | B44: 2000 | C44: 8000 | D44: Confirmed — $2,000/week · $333.33/day · absent days deducted
A45: Current roster: John + Debi + Samu (no mesero) | B45: 12050 | C45: 23750 | D45: 24550 | E45: 3758 | F45: Cesar resigned — fixed costs down $2,000/wk | G45: Break-even ≈ $3,758/day (fixed $12,050 + variable $10,500, ÷6 days)
A47: ── BREAK-EVEN & WEEKLY REVENUE TARGETS ──
A48: SCENARIO | B48: Fixed Costs ($) | C48: Avg Variable Costs ($) | D48: MIN Weekly Revenue ($) | E48: MIN Daily Revenue ($) | F48: Current Avg/Day ($) | G48: STATUS
A49: Without Mesero (NOW) | B49: 11250 | C49: 10500 | D49: 21750 | E49: 3625 | F49: 4011 | G49: ✅ Above break-even — revised down from $3,792 → $3,625/day | H49: ✅ Current scenario — no mesero (Judith resigned 7 Jun)
A50: With Mesero (~$2,250) | B50: 13500 | C50: 10500 | D50: 24000 | E50: 4000 | F50: 4011 | G50: ⚠️ Still below — need +$-11/day when mesero hired | H50: ⏳ Will update when 2 new staff details confirmed (9 Jun)
A51: Safety buffer (+15%) | B51: 11250 | C51: 10500 | D51: 25012 | E51: 4169 | F51: 4011 | G51: Target for healthy buffer: $4,169/day
A53: NOTES:
A54: Variable costs = avg ingredients + supplies per week based on Weeks 1-2 actual data (~$10,500)
A55: Break-even revised: Rent+Maintenance confirmed $20,000/mo · Utilities est. $4,000/mo → Total overhead $24,000/mo
A56: Min daily (no mesero): $3,625 · With mesero: $4,000 · Comfortable target: $4,169+/day
A57: Utilities (electricity+gas) ~$4,000/mo is ESTIMATED — update when bills arrive
A61: ── PROPINAS / TIPS PASS-THROUGH (NOT income, NOT expense) ──
A62: Date | B62: Paid To | D62: Amount
A63: 46165 | B63: John (6 dias) | D63: 515
A64: 46165 | B64: Debi (6 dias) | D64: 515
A65: 46165 | B65: Victor (2 dias) | D65: 168
A66: 46174 | B66: John (Week 2) | D66: 350
A67: 46174 | B67: Duvi/Debi (Week 2) | D67: 350
A68: 46186 | B68: John (Week 4) | D68: 200
A69: 46186 | B69: Duvi/Debi (Week 4) | D69: 200
A70: 46186 | B70: Cesar (Week 4) | D70: 126
A71: 46186 | B71: Samu (Week 4) | D71: 126
A72: 46193 | B72: Duvi/Debi (Week 5 partial) | D72: 120
A73: 46193 | B73: John (Week 5 partial) | D73: 150
A74: 46193 | B74: Samu (Week 5) | D74: 100
B93: TOTAL TIPS PASSED THROUGH | D93: =SUM(D63:D92)
A94: Customer tips collected & handed to staff. Excluded from P&L — nets to zero (received = paid).
A96: ── CASH RECONCILIATION (15 Jun 2026) ──
A97: Actual restaurant cash on hand | D97: 20283
A98: Adjustment: restaurant cash added to tips + Mercado Pago commission (vs running estimate) | D98: -165
A99: Reconciled to physical count provided by Reddy. $20,283 is net of MP % deductions.

Sheet 🚚 Suppliers
A2: 🚚 LOKA — SUPPLIER ORDERS | F2: Track purchase orders from suppliers
B5: TOTAL ORDERS | C5: PENDING | D5: IN TRANSIT | E5: RECEIVED | F5: MONTH SPEND | G5: PENDING VALUE | H5: PENDING COUNT
B6: =COUNTA(C9:C308)-1 | C6: =COUNTIF(K9:K308,"Pending") | D6: =COUNTIF(K9:K308,"In Transit") | E6: =COUNTIF(K9:K308,"Received") | F6: =SUMIF(K9:K308,"Received",J9:J308) | G6: =SUMIF(K9:K308,"Pending",J9:J308) | H6: =COUNTIF(K9:K308,"Pending")+COUNTIF(K9:K308,"In Transit")

Sheet 📋 Supplier Directory
B2: 📋 LOKA — SUPPLIER DIRECTORY
B3: Contact list for all regular suppliers
B6: Supplier Name | C6: Contact / Phone | D6: Products Supplied | E6: Location / Address | F6: Notes
B7: Girigallo | C7: 442-249-4707 | D7: Pollo | E7: Islas Aleutianas 134, Loma Linda, C.P 76070
B8: Alico | C8: 442-796-8876 | D8: Carne de hamburguesa, Papas, Boneless | E8: Cerro de las Campanas 173, Col. Las Americas
B9: Reca (Repartidor) | C9: 442-679-6651 | D9: Aguas Avia / Bebidas | E9: — | F9: Delivery supplier
B10: Toluco | C10: — | D10: Desechables (Plasticos) | E10: Plásticos Desechables el Toluco, C/ 15 de Mayo 189, La Santa Cruz, Centro, 76020 Santiago de Querétaro
B11: Bodega del Queso | C11: 442-114-0827 | D11: Queso, Jamon, Crema | E11: Avenida Universidad 119, Los Cedros, 76165 Santiago de Querétaro, Qro.
B12: Panadería Real | C12: 442-379-1880 | D12: Pan hamburguesa, Mayonesa, Arrachera, Sandwhich | E12: Plaza Capuchinas 149, Central de Abasto, Querétaro | F12: Also supplies at Brisa del Mar area
B13: Etrusca | C13: 442-234-5077 | D13: Sabores de Frappe, Matcha, Taro | E13: Café Etrusca Querétaro, Av. Tecnológico 10-Sur, Niños Héroes, 76010 Santiago de Querétaro
B16: Note: Additional suppliers recorded in expenses — Brisa del Mar, Chedraui, Costco, Real Abastos, OXXO, Pescadería El Faro

Sheet 📈 Monthly P&L
A1: LOKA — MONTHLY P&L (live formulas — auto-updates from Daily Log & Expenses)
A3: SUMMARY | B3: May 2026 | C3: Jun 2026 | D3: Jul 2026
A4: Total Income | B4: =SUMIFS('📅 Daily Log'!$F$8:$F$500,'📅 Daily Log'!$B$8:$B$500,">="&DATE(2026,5,1),'📅 Daily Log'!$B$8:$B$500,"<"&DATE(2026,6,1)) | C4: =SUMIFS('📅 Daily Log'!$F$8:$F$500,'📅 Daily Log'!$B$8:$B$500,">="&DATE(2026,6,1),'📅 Daily Log'!$B$8:$B$500,"<"&DATE(2026,7,1)) | D4: =SUMIFS('📅 Daily Log'!$F$8:$F$500,'📅 Daily Log'!$B$8:$B$500,">="&DATE(2026,7,1),'📅 Daily Log'!$B$8:$B$500,"<"&DATE(2026,8,1))
A5: Total Expenses | B5: =SUMIFS('💸 Expenses'!$F$8:$F$500,'💸 Expenses'!$B$8:$B$500,">="&DATE(2026,5,1),'💸 Expenses'!$B$8:$B$500,"<"&DATE(2026,6,1)) | C5: =SUMIFS('💸 Expenses'!$F$8:$F$500,'💸 Expenses'!$B$8:$B$500,">="&DATE(2026,6,1),'💸 Expenses'!$B$8:$B$500,"<"&DATE(2026,7,1)) | D5: =SUMIFS('💸 Expenses'!$F$8:$F$500,'💸 Expenses'!$B$8:$B$500,">="&DATE(2026,7,1),'💸 Expenses'!$B$8:$B$500,"<"&DATE(2026,8,1))
A6: NET PROFIT / LOSS | B6: =B4-B5 | C6: =C4-C5 | D6: =D4-D5
A7: Trading Days | B7: =COUNTIFS('📅 Daily Log'!$F$8:$F$500,">0",'📅 Daily Log'!$B$8:$B$500,">="&DATE(2026,5,1),'📅 Daily Log'!$B$8:$B$500,"<"&DATE(2026,6,1)) | C7: =COUNTIFS('📅 Daily Log'!$F$8:$F$500,">0",'📅 Daily Log'!$B$8:$B$500,">="&DATE(2026,6,1),'📅 Daily Log'!$B$8:$B$500,"<"&DATE(2026,7,1)) | D7: =COUNTIFS('📅 Daily Log'!$F$8:$F$500,">0",'📅 Daily Log'!$B$8:$B$500,">="&DATE(2026,7,1),'📅 Daily Log'!$B$8:$B$500,"<"&DATE(2026,8,1))
A8: Avg Income / Day | B8: =IFERROR(B4/B7,0) | C8: =IFERROR(C4/C7,0) | D8: =IFERROR(D4/D7,0)
A10: INCOME BY TYPE | B10: May 2026 | C10: Jun 2026 | D10: Jul 2026
A11: Card | B11: =SUMIFS('📅 Daily Log'!$D$8:$D$500,'📅 Daily Log'!$B$8:$B$500,">="&DATE(2026,5,1),'📅 Daily Log'!$B$8:$B$500,"<"&DATE(2026,6,1)) | C11: =SUMIFS('📅 Daily Log'!$D$8:$D$500,'📅 Daily Log'!$B$8:$B$500,">="&DATE(2026,6,1),'📅 Daily Log'!$B$8:$B$500,"<"&DATE(2026,7,1)) | D11: =SUMIFS('📅 Daily Log'!$D$8:$D$500,'📅 Daily Log'!$B$8:$B$500,">="&DATE(2026,7,1),'📅 Daily Log'!$B$8:$B$500,"<"&DATE(2026,8,1))
A12: Cash | B12: =SUMIFS('📅 Daily Log'!$E$8:$E$500,'📅 Daily Log'!$B$8:$B$500,">="&DATE(2026,5,1),'📅 Daily Log'!$B$8:$B$500,"<"&DATE(2026,6,1)) | C12: =SUMIFS('📅 Daily Log'!$E$8:$E$500,'📅 Daily Log'!$B$8:$B$500,">="&DATE(2026,6,1),'📅 Daily Log'!$B$8:$B$500,"<"&DATE(2026,7,1)) | D12: =SUMIFS('📅 Daily Log'!$E$8:$E$500,'📅 Daily Log'!$B$8:$B$500,">="&DATE(2026,7,1),'📅 Daily Log'!$B$8:$B$500,"<"&DATE(2026,8,1))
A13: Transfer | B13: =SUMIFS('📅 Daily Log'!$G$8:$G$500,'📅 Daily Log'!$B$8:$B$500,">="&DATE(2026,5,1),'📅 Daily Log'!$B$8:$B$500,"<"&DATE(2026,6,1)) | C13: =SUMIFS('📅 Daily Log'!$G$8:$G$500,'📅 Daily Log'!$B$8:$B$500,">="&DATE(2026,6,1),'📅 Daily Log'!$B$8:$B$500,"<"&DATE(2026,7,1)) | D13: =SUMIFS('📅 Daily Log'!$G$8:$G$500,'📅 Daily Log'!$B$8:$B$500,">="&DATE(2026,7,1),'📅 Daily Log'!$B$8:$B$500,"<"&DATE(2026,8,1))
A14: Total Income | B14: =B11+B12+B13 | C14: =C11+C12+C13 | D14: =D11+D12+D13
A16: EXPENSES BY CATEGORY (high → low) | B16: May 2026 | C16: Jun 2026 | D16: Jul 2026
A17: Staff - Salary | B17: =SUMIFS('💸 Expenses'!$F$8:$F$500,'💸 Expenses'!$E$8:$E$500,$A17,'💸 Expenses'!$B$8:$B$500,">="&DATE(2026,5,1),'💸 Expenses'!$B$8:$B$500,"<"&DATE(2026,6,1)) | C17: =SUMIFS('💸 Expenses'!$F$8:$F$500,'💸 Expenses'!$E$8:$E$500,$A17,'💸 Expenses'!$B$8:$B$500,">="&DATE(2026,6,1),'💸 Expenses'!$B$8:$B$500,"<"&DATE(2026,7,1)) | D17: =SUMIFS('💸 Expenses'!$F$8:$F$500,'💸 Expenses'!$E$8:$E$500,$A17,'💸 Expenses'!$B$8:$B$500,">="&DATE(2026,7,1),'💸 Expenses'!$B$8:$B$500,"<"&DATE(2026,8,1))
A18: Rent | B18: =SUMIFS('💸 Expenses'!$F$8:$F$500,'💸 Expenses'!$E$8:$E$500,$A18,'💸 Expenses'!$B$8:$B$500,">="&DATE(2026,5,1),'💸 Expenses'!$B$8:$B$500,"<"&DATE(2026,6,1)) | C18: =SUMIFS('💸 Expenses'!$F$8:$F$500,'💸 Expenses'!$E$8:$E$500,$A18,'💸 Expenses'!$B$8:$B$500,">="&DATE(2026,6,1),'💸 Expenses'!$B$8:$B$500,"<"&DATE(2026,7,1)) | D18: =SUMIFS('💸 Expenses'!$F$8:$F$500,'💸 Expenses'!$E$8:$E$500,$A18,'💸 Expenses'!$B$8:$B$500,">="&DATE(2026,7,1),'💸 Expenses'!$B$8:$B$500,"<"&DATE(2026,8,1))
A19: Ingredients - Meat | B19: =SUMIFS('💸 Expenses'!$F$8:$F$500,'💸 Expenses'!$E$8:$E$500,$A19,'💸 Expenses'!$B$8:$B$500,">="&DATE(2026,5,1),'💸 Expenses'!$B$8:$B$500,"<"&DATE(2026,6,1)) | C19: =SUMIFS('💸 Expenses'!$F$8:$F$500,'💸 Expenses'!$E$8:$E$500,$A19,'💸 Expenses'!$B$8:$B$500,">="&DATE(2026,6,1),'💸 Expenses'!$B$8:$B$500,"<"&DATE(2026,7,1)) | D19: =SUMIFS('💸 Expenses'!$F$8:$F$500,'💸 Expenses'!$E$8:$E$500,$A19,'💸 Expenses'!$B$8:$B$500,">="&DATE(2026,7,1),'💸 Expenses'!$B$8:$B$500,"<"&DATE(2026,8,1))
A20: Ingredients - Vegetables | B20: =SUMIFS('💸 Expenses'!$F$8:$F$500,'💸 Expenses'!$E$8:$E$500,$A20,'💸 Expenses'!$B$8:$B$500,">="&DATE(2026,5,1),'💸 Expenses'!$B$8:$B$500,"<"&DATE(2026,6,1)) | C20: =SUMIFS('💸 Expenses'!$F$8:$F$500,'💸 Expenses'!$E$8:$E$500,$A20,'💸 Expenses'!$B$8:$B$500,">="&DATE(2026,6,1),'💸 Expenses'!$B$8:$B$500,"<"&DATE(2026,7,1)) | D20: =SUMIFS('💸 Expenses'!$F$8:$F$500,'💸 Expenses'!$E$8:$E$500,$A20,'💸 Expenses'!$B$8:$B$500,">="&DATE(2026,7,1),'💸 Expenses'!$B$8:$B$500,"<"&DATE(2026,8,1))
A21: Ingredients - Pantry | B21: =SUMIFS('💸 Expenses'!$F$8:$F$500,'💸 Expenses'!$E$8:$E$500,$A21,'💸 Expenses'!$B$8:$B$500,">="&DATE(2026,5,1),'💸 Expenses'!$B$8:$B$500,"<"&DATE(2026,6,1)) | C21: =SUMIFS('💸 Expenses'!$F$8:$F$500,'💸 Expenses'!$E$8:$E$500,$A21,'💸 Expenses'!$B$8:$B$500,">="&DATE(2026,6,1),'💸 Expenses'!$B$8:$B$500,"<"&DATE(2026,7,1)) | D21: =SUMIFS('💸 Expenses'!$F$8:$F$500,'💸 Expenses'!$E$8:$E$500,$A21,'💸 Expenses'!$B$8:$B$500,">="&DATE(2026,7,1),'💸 Expenses'!$B$8:$B$500,"<"&DATE(2026,8,1))
A22: Ingredients - Beverages | B22: =SUMIFS('💸 Expenses'!$F$8:$F$500,'💸 Expenses'!$E$8:$E$500,$A22,'💸 Expenses'!$B$8:$B$500,">="&DATE(2026,5,1),'💸 Expenses'!$B$8:$B$500,"<"&DATE(2026,6,1)) | C22: =SUMIFS('💸 Expenses'!$F$8:$F$500,'💸 Expenses'!$E$8:$E$500,$A22,'💸 Expenses'!$B$8:$B$500,">="&DATE(2026,6,1),'💸 Expenses'!$B$8:$B$500,"<"&DATE(2026,7,1)) | D22: =SUMIFS('💸 Expenses'!$F$8:$F$500,'💸 Expenses'!$E$8:$E$500,$A22,'💸 Expenses'!$B$8:$B$500,">="&DATE(2026,7,1),'💸 Expenses'!$B$8:$B$500,"<"&DATE(2026,8,1))
A23: Ingredients - Dairy | B23: =SUMIFS('💸 Expenses'!$F$8:$F$500,'💸 Expenses'!$E$8:$E$500,$A23,'💸 Expenses'!$B$8:$B$500,">="&DATE(2026,5,1),'💸 Expenses'!$B$8:$B$500,"<"&DATE(2026,6,1)) | C23: =SUMIFS('💸 Expenses'!$F$8:$F$500,'💸 Expenses'!$E$8:$E$500,$A23,'💸 Expenses'!$B$8:$B$500,">="&DATE(2026,6,1),'💸 Expenses'!$B$8:$B$500,"<"&DATE(2026,7,1)) | D23: =SUMIFS('💸 Expenses'!$F$8:$F$500,'💸 Expenses'!$E$8:$E$500,$A23,'💸 Expenses'!$B$8:$B$500,">="&DATE(2026,7,1),'💸 Expenses'!$B$8:$B$500,"<"&DATE(2026,8,1))
A24: Supplies / Other | B24: =SUMIFS('💸 Expenses'!$F$8:$F$500,'💸 Expenses'!$E$8:$E$500,$A24,'💸 Expenses'!$B$8:$B$500,">="&DATE(2026,5,1),'💸 Expenses'!$B$8:$B$500,"<"&DATE(2026,6,1)) | C24: =SUMIFS('💸 Expenses'!$F$8:$F$500,'💸 Expenses'!$E$8:$E$500,$A24,'💸 Expenses'!$B$8:$B$500,">="&DATE(2026,6,1),'💸 Expenses'!$B$8:$B$500,"<"&DATE(2026,7,1)) | D24: =SUMIFS('💸 Expenses'!$F$8:$F$500,'💸 Expenses'!$E$8:$E$500,$A24,'💸 Expenses'!$B$8:$B$500,">="&DATE(2026,7,1),'💸 Expenses'!$B$8:$B$500,"<"&DATE(2026,8,1))
A25: Supermarket/General | B25: =SUMIFS('💸 Expenses'!$F$8:$F$500,'💸 Expenses'!$E$8:$E$500,$A25,'💸 Expenses'!$B$8:$B$500,">="&DATE(2026,5,1),'💸 Expenses'!$B$8:$B$500,"<"&DATE(2026,6,1)) | C25: =SUMIFS('💸 Expenses'!$F$8:$F$500,'💸 Expenses'!$E$8:$E$500,$A25,'💸 Expenses'!$B$8:$B$500,">="&DATE(2026,6,1),'💸 Expenses'!$B$8:$B$500,"<"&DATE(2026,7,1)) | D25: =SUMIFS('💸 Expenses'!$F$8:$F$500,'💸 Expenses'!$E$8:$E$500,$A25,'💸 Expenses'!$B$8:$B$500,">="&DATE(2026,7,1),'💸 Expenses'!$B$8:$B$500,"<"&DATE(2026,8,1))
A26: Ingredients - Bread | B26: =SUMIFS('💸 Expenses'!$F$8:$F$500,'💸 Expenses'!$E$8:$E$500,$A26,'💸 Expenses'!$B$8:$B$500,">="&DATE(2026,5,1),'💸 Expenses'!$B$8:$B$500,"<"&DATE(2026,6,1)) | C26: =SUMIFS('💸 Expenses'!$F$8:$F$500,'💸 Expenses'!$E$8:$E$500,$A26,'💸 Expenses'!$B$8:$B$500,">="&DATE(2026,6,1),'💸 Expenses'!$B$8:$B$500,"<"&DATE(2026,7,1)) | D26: =SUMIFS('💸 Expenses'!$F$8:$F$500,'💸 Expenses'!$E$8:$E$500,$A26,'💸 Expenses'!$B$8:$B$500,">="&DATE(2026,7,1),'💸 Expenses'!$B$8:$B$500,"<"&DATE(2026,8,1))
A27: Supermarket / General | B27: =SUMIFS('💸 Expenses'!$F$8:$F$500,'💸 Expenses'!$E$8:$E$500,$A27,'💸 Expenses'!$B$8:$B$500,">="&DATE(2026,5,1),'💸 Expenses'!$B$8:$B$500,"<"&DATE(2026,6,1)) | C27: =SUMIFS('💸 Expenses'!$F$8:$F$500,'💸 Expenses'!$E$8:$E$500,$A27,'💸 Expenses'!$B$8:$B$500,">="&DATE(2026,6,1),'💸 Expenses'!$B$8:$B$500,"<"&DATE(2026,7,1)) | D27: =SUMIFS('💸 Expenses'!$F$8:$F$500,'💸 Expenses'!$E$8:$E$500,$A27,'💸 Expenses'!$B$8:$B$500,">="&DATE(2026,7,1),'💸 Expenses'!$B$8:$B$500,"<"&DATE(2026,8,1))
A28: Maintenance | B28: =SUMIFS('💸 Expenses'!$F$8:$F$500,'💸 Expenses'!$E$8:$E$500,$A28,'💸 Expenses'!$B$8:$B$500,">="&DATE(2026,5,1),'💸 Expenses'!$B$8:$B$500,"<"&DATE(2026,6,1)) | C28: =SUMIFS('💸 Expenses'!$F$8:$F$500,'💸 Expenses'!$E$8:$E$500,$A28,'💸 Expenses'!$B$8:$B$500,">="&DATE(2026,6,1),'💸 Expenses'!$B$8:$B$500,"<"&DATE(2026,7,1)) | D28: =SUMIFS('💸 Expenses'!$F$8:$F$500,'💸 Expenses'!$E$8:$E$500,$A28,'💸 Expenses'!$B$8:$B$500,">="&DATE(2026,7,1),'💸 Expenses'!$B$8:$B$500,"<"&DATE(2026,8,1))
... A43: Ingredients - Produce | B43: =SUMIFS('💸 Expenses'!$F$8:$F$500,'💸 Expenses'!$E$8:$E$500,$A43,'💸 Expenses'!$B$8:$B$500,">="&DATE(2026,5,1),'💸 Expenses'!$B$8:$B$500,"<"&DATE(2026,6,1)) | C43: =SUMIFS('💸 Expenses'!$F$8:$F$500,'💸 Expenses'!$E$8:$E$500,$A43,'💸 Expenses'!$B$8:$B$500,">="&DATE(2026,6,1),'💸 Expenses'!$B$8:$B$500,"<"&DATE(2026,7,1)) | D43: =SUMIFS('💸 Expenses'!$F$8:$F$500,'💸 Expenses'!$E$8:$E$500,$A43,'💸 Expenses'!$B$8:$B$500,">="&DATE(2026,7,1),'💸 Expenses'!$B$8:$B$500,"<"&DATE(2026,8,1))
A44: TOTAL EXPENSES | B44: =SUMIFS('💸 Expenses'!$F$8:$F$500,'💸 Expenses'!$B$8:$B$500,">="&DATE(2026,5,1),'💸 Expenses'!$B$8:$B$500,"<"&DATE(2026,6,1)) | C44: =SUMIFS('💸 Expenses'!$F$8:$F$500,'💸 Expenses'!$B$8:$B$500,">="&DATE(2026,6,1),'💸 Expenses'!$B$8:$B$500,"<"&DATE(2026,7,1)) | D44: =SUMIFS('💸 Expenses'!$F$8:$F$500,'💸 Expenses'!$B$8:$B$500,">="&DATE(2026,7,1),'💸 Expenses'!$B$8:$B$500,"<"&DATE(2026,8,1))
A45: NET PROFIT / LOSS | B45: =B4-B44 | C45: =C4-C44 | D45: =D4-D44

Sheet 📥 Pending Income
B2: LOKA CAFE RESTAURANTE — PENDING INCOME / RECEIVABLES | C2: LOKA CAFE RESTAURANTE — PENDING INCOME / RECEIVABLES | D2: LOKA CAFE RESTAURANTE — PENDING INCOME / RECEIVABLES | E2: LOKA CAFE RESTAURANTE — PENDING INCOME / RECEIVABLES | F2: LOKA CAFE RESTAURANTE — PENDING INCOME / RECEIVABLES | G2: LOKA CAFE RESTAURANTE — PENDING INCOME / RECEIVABLES | H2: LOKA CAFE RESTAURANTE — PENDING INCOME / RECEIVABLES | I2: LOKA CAFE RESTAURANTE — PENDING INCOME / RECEIVABLES
B4: Date Served | C4: Client | D4: Description | E4: Qty | F4: Unit Price ($) | G4: Total Amount ($) | H4: Status | I4: Notes
B5: 21-May-2026 | C5: Government Finances Dept. | D5: Catering order — 25 plates | E5: 25 | F5: 140 | G5: 3500 | H5: ⏳ NOT YET PAID | I5: Awaiting payment — follow up with client
B7: TOTAL PENDING | G7: 3500

Sheet 💰 Owner Ledger
A1: LOHITH — OWNER LEDGER & PERSONAL BALANCE TRACKER
A3: Date | B3: Description | C3: Type | D3: Spent by Lohith ($) | E3: Transferred to Lohith ($) | F3: Running Balance ($) | G3: Status | H3: Notes
A4: 46174 | B4: Telmex Internet Bill (Mayo) | C4: Expense - Personal | D4: 349 | F4: =IFERROR(D4-E4,0) | G4: ⏳ Reimburse | H4: Paid by Lohith — ⏳ Reimburse
A5: 46174 | B5: Customer Transfer — Jun 1 | C5: Transfer Received | E5: 310 | F5: =IFERROR(F4+D5-E5,0) | G5: ✅ | H5: ✅ Received in Lohith account
A6: 46175 | B6: Customer Transfer — Jun 2 | C6: Transfer Received | E6: 283 | F6: =IFERROR(F5+D6-E6,0) | G6: ✅ | H6: ✅ Received in Lohith account
A7: 46176 | B7: Customer Transfer — Jun 3 | C7: Transfer Received | E7: 120 | F7: =IFERROR(F6+D7-E7,0) | G7: ✅ | H7: ✅ Received in Lohith account
A8: 46177 | B8: Personal expenses — Huevos, Ajonjoli, Verduras | C8: Expense - Personal | D8: 358 | F8: =IFERROR(F7+D8-E8,0) | G8: ⏳ Reimburse | H8: $69 Huevos + $44 Ajonjoli Blanco + $45 Ajonjoli Negro + $200 Verduras
A9: 46177 | B9: Cash settlement — $6 added to restaurant | C9: Expense - Personal | D9: 6 | F9: =IFERROR(F8+D9-E9,0) | G9: ✅ Settled | H9: Lohith added $6 cash to restaurant — balance now ZERO
A10: 46178 | B10: Customer Transfer — Jun 5 | C10: Transfer Received | E10: 135 | F10: =IFERROR(F9+D10-E10,0) | G10: ✅ Received | H10: ✅ Received in Lohith account — Jun 5
A11: 46177 | B11: Renta + Mantenimiento Junio 2026 | C11: Expense - Personal | D11: 20000 | F11: =IFERROR(F10+D11-E11,0) | G11: ⏳ Reimburse | H11: Rent $15,000 + Maintenance $5,000 — paid personally by Lohith on 4 Jun
A12: 46181 | B12: Customer Transfer — Jun 8 | C12: Transfer Received | E12: 99 | F12: =IFERROR(F11+D12-E12,0) | G12: ✅ Received | H12: ✅ Received in Lohith account — Jun 8
A13: 46183 | B13: Chedraui Paseo — Groceries (elote, chile, tomate, tortillas, bolillo) | C13: Expense - Personal | D13: 236.81 | F13: =IFERROR(F12+D13-E13,0) | G13: ⏳ Reimburse | H13: Paid personally by Lohith — HSBC **5543
A14: 46183 | B14: Office Depot — Comanda Restaurante | C14: Expense - Personal | D14: 59 | F14: =IFERROR(F13+D14-E14,0) | G14: ⏳ Reimburse | H14: Paid personally by Lohith — MC **5543
A15: 46184 | B15: ALICO — Ala de Pollo, Papa Harvest 13.62kg, Boneless Freskecito | C15: Expense - Personal | D15: 2865 | F15: =IFERROR(F14+D15-E15,0) | G15: ⏳ Reimburse | H15: Restaurant ingredients paid personally by Lohith (transfer) — 11 Jun
A16: 46184 | B16: Pollería — Muslo de Pollo 4.70 kg | C16: Expense - Personal | D16: 235 | F16: =IFERROR(F15+D16-E16,0) | G16: ⏳ Reimburse | H16: Restaurant ingredients paid personally by Lohith (transfer) — 11 Jun
A17: 46188 | B17: Chedraui — Tortillas, Bolillo, Rosca de Nuez | C17: Expense - Personal | D17: 160.33 | F17: =IFERROR(F16+D17-E17,0) | G17: ⏳ Reimburse | H17: HSBC **5543 — paid by Lohith 15 Jun
A18: 46188 | B18: OXXO Pathe — Aceite Vegetal (2) | C18: Expense - Personal | D18: 104 | F18: =IFERROR(F17+D18-E18,0) | G18: ⏳ Reimburse | H18: HSBC **5543 — paid by Lohith 15 Jun
A19: 46188 | B19: Miscelánea LC — Ribeye, Chuleta, Bistec | C19: Expense - Personal | D19: 1015 | F19: =IFERROR(F18+D19-E19,0) | G19: ⏳ Reimburse | H19: HSBC **5543 — paid by Lohith 15 Jun
A20: 46188 | B20: Transfer from Restaurant account | C20: Reimbursement | E20: 3162 | F20: =IFERROR(F19+D20-E20,0) | G20: ✅ Received | H20: Bank transfer to Lohith
A21: 46188 | B21: 15 Jun card expenses reimbursed (Chedraui+OXXO+Miscelánea) | C21: Reimbursement | E21: 1279.33 | F21: =IFERROR(F20+D21-E21,0) | G21: ✅ Received | H21: HSBC **5543 items repaid same day
A22: 46189 | B22: OXXO Pathe — Leche Lala UHT (2) | C22: Expense - Personal | D22: 93 | F22: =IFERROR(F21+D22-E22,0) | G22: ⏳ Reimburse | H22: HSBC **5543 — paid by Lohith 16 Jun
A23: 46189 | B23: 16 Jun OXXO card expense reimbursed | C23: Reimbursement | E23: 93 | F23: =IFERROR(F22+D23-E23,0) | G23: ✅ Received | H23: HSBC **5543 item repaid same day
A24: 46191 | B24: Customer Transfer — Jun 18 (revenue paid into Lohith account) | C24: Transfer Received | E24: 400 | F24: =IFERROR(F23+D24-E24,0) | G24: ✅ Received | H24: Customer paid $400 by transfer into Lohith account — counts against balance owed
A25: 46192 | B25: Customer Transfer — Jun 19 (revenue paid into Lohith account) | C25: Transfer Received | E25: 120 | F25: =IFERROR(F24+D25-E25,0) | G25: ✅ Received | H25: Customer paid \ by transfer into Lohith account — counts against balance owed
A26: 46199 | B26: Customer Transfer - Jun 26 (revenue paid into Lohith account) | C26: Transfer Received | E26: 165 | F26: =IFERROR(F25+D26-E26,0) | G26: ✅ Received | H26: Customer paid $165 by transfer into Lohith account - counts against balance owed
A27: 46202 | B27: Cash withdrawal by Lohith from restaurant (partial repayment of balance owed) | C27: Cash Withdrawal | E27: 10000 | F27: =IFERROR(F26+D27-E27,0) | G27: ✅ Taken | H27: Took $10,000 cash from restaurant till; deducted from balance owed and from restaurant cash on hand
A28: 46173 | B28: Renta media mensualidad Mayo 2026 (duenos anteriores) - paid by Lohith | C28: Expense - Personal | D28: 10000 | F28: =IFERROR(F27+D28-E28,0) | G28: ⏳ Reimburse | H28: May half-month rent fronted by Lohith; reimbursable
A29: 46203 | B29: Owner balance settled from restaurant capital budget (paid from Remaining-with-Lohith) | C29: Settlement | E29: 19314.81 | F29: =IFERROR(F28+D29-E29,0) | G29: ✅ Settled from budget | H29: Full owner ledger balance ($19,315 rent + fronted operating items) settled against capital budget remaining with Lohith. Going forward, rent & operating costs funded from allocated budget.
A30: 46203 | B30: Customer transfer-to-me 30-Jun | C30: Transfer Received | E30: 55 | F30: =IFERROR(F29+D30-E30,0) | G30: ✅ Received | H30: Customer paid 55 via direct transfer to Lohith instead of restaurant card/cash
A31: 46210 | B31: HEB — Dustbin covers + Pan cutting knife | C31: Expense - Personal | D31: 205 | F31: =IFERROR(F30+D31-E31,0) | G31: ✅ Settled | H31: Paid personally by Lohith (HEB) — dustbin covers + pan cutting knife; reimbursable
A32: 46210 | B32: Transfer from restaurant — net settlement | C32: Reimbursement | E32: 150 | F32: =IFERROR(F31+D32-E32,0) | G32: ✅ Settled | H32: Net $150 = $205 HEB expense − $55 Lohith owed to restaurant; balance now ZERO
A33: 46211 | B33: GUIMAR — Vasos de plástico + tapas | C33: Expense - Personal | D33: 73.5 | F33: =IFERROR(F32+D33-E33,0) | G33: ⏳ Reimburse | H33: Paid by Lohith (GUIMAR receipt, 08-Jul): vasos plast. $41 + reyma tapa vaso $32.50 = $73.50; reimbursable
A34: 46211 | B34: Transfer-to-me (customer payment 08-Jul) | C34: Transfer Received | E34: 195 | F34: =IFERROR(F33+D34-E34,0) | G34: ✅ Received | H34: Customer paid $195 by transfer to Lohith (counts as 08-Jul revenue; cash went to Lohith not the till)
A35: 46212 | B35: Transfer-to-me (customer payment 09-Jul) | C35: Transfer Received | E35: 120 | F35: =IFERROR(F34+D35-E35,0) | G35: ✅ Received | H35: Customer paid $120 by transfer to Lohith (09-Jul revenue; cash to Lohith not till)
A36: 46213 | B36: Transfer-to-me (customer payment 10-Jul) | C36: Transfer Received | E36: 70 | F36: =IFERROR(F35+D36-E36,0) | G36: ✅ Received | H36: Customer paid $70 by transfer to Lohith (10-Jul revenue; cash to Lohith not till)
A37: TOTALS & CURRENT BALANCE | D37: =SUM(D4:D36) | E37: =SUM(E4:E36) | F37: =F36 | G37: =IF(F36>0,"Restaurant owes Lohith $"&TEXT(F36,"#,##0"),IF(F36<0,"Lohith holds $"&TEXT(ABS(F36),"#,##0"),"Zero balance"))
