Workbook

Sheet Capital & Ownership
B1: LOKA — CAPITAL, OWNERSHIP & PRE-OPENING EXPENSES
B2: Last updated: 25 May 2026 | Blue = hardcoded inputs Yellow = add new expenses here
B4: A. OWNERSHIP STRUCTURE
B5: Owner | C5: Share % | D5: Capital ($) | E5: Expenses ($) | F5: Remaining ($) | G5: Role / Notes
B6: Lohith Reddy | C6: 0.5 | D6: 300000 | E6: =D47 | F6: =D6-E6 | G6: 50% — Managing Partner
B7: Kashigoud Patil | C7: 0.3 | D7: 180000 | E7: =D34 | F7: =D7-E7 | G7: 30% — Partner
B8: Shashirekha Basavaraju | C8: 0.2 | D8: 120000 | E8: =D59 | F8: =D8-E8 | G8: 20% — Partner
B9: TOTAL | C9: =SUM(C6:C8) | D9: =SUM(D6:D8) | E9: =SUM(E6:E8) | F9: =SUM(F6:F8)
B11: B. RESTAURANT ACQUISITION — $390,000 TOTAL
B12: Description | C12: Date | D12: Amount ($) | E12: Paid By | F12: Status | G12: Notes
B13: TOTAL Purchase Price — Previous Owners | D13: 390000 | E13: All Partners | F13: ⚠️ PARTIALLY PAID — $164,500 remaining | G13: Full acquisition amount
B14: Advance Payment (paid by Lohith) | D14: 5000 | E14: Lohith Reddy | F14: ✅ PAID | G14: Advance to previous owners
B15: Payment to Previous Owners | C15: 46176 | D15: 95000 | E15: Lohith Reddy | F15: ✅ PAID | G15: Paid from restaurant operating balance — 3 Jun 2026
B16: Payment to Previous Owner — Account 1 | C16: 46177 | D16: 8000 | E16: Lohith Reddy | F16: ✅ PAID | G16: Capital payment — from main budget — transferred to different accounts
B17: Payment to Previous Owner — Account 2
B18: Payment to Previous Owner — Account 3 | C18: 46177 | D18: 15000 | E18: Lohith Reddy | F18: ✅ PAID | G18: Capital payment — from main budget — transferred to different accounts
B19: Payment to Previous Owner — Account 4 | C19: 46177 | D19: 10000 | E19: Lohith Reddy | F19: ✅ PAID | G19: Capital payment — from main budget — transferred to different accounts
B20: Payment to Previous Owner — Account 5 | C20: 46177 | D20: 44000 | E20: Lohith Reddy | F20: ✅ PAID | G20: Capital payment — from main budget — transferred to different accounts
B21: Payment to Previous Owner — Account 6 | C21: 46177 | D21: 44000 | E21: Lohith Reddy | F21: ✅ PAID | G21: Capital payment — from main budget — transferred to different accounts
B22: Balance Remaining | D22: =D13-SUM(D14:D21) | E22: — | F22: ⏳ PENDING | G22: $390,000 total − $225,500 paid = $164,500 remaining
B24: PAYMENT BREAKDOWN — How the $390,000 will be funded
B25: Source | C25: From | D25: Amount ($) | E25: Toward % | F25: Cumulative | G25: Notes
B26: Kashigoud Transfer to Lohith | C26: Kashigoud Patil | D26: 125000 | E26: =D19/390000 | F26: =D19 | G26: Full Kashi transfer
B27: Shashirekha Transfer to Lohith | C27: Shashirekha B. | D27: 100000 | E27: =D20/390000 | F27: =D19+D20 | G27: Full Shashi transfer
B28: Lohith Reddy (own funds) | C28: Lohith Reddy | D28: =390000-D19-D20 | E28: =D21/390000 | F28: =D20+D21 | G28: Balance from Lohith
B29: Advance Already Paid | C29: Lohith Reddy | D29: 5000 | E29: =D22/390000 | F29: Paid ✅ | G29: Already paid
B31: C. PRE-OPENING EXPENSES — KASHIGOUD PATIL
B32: Description | C32: Date | D32: Amount ($) | E32: Paid To | F32: Category | G32: Notes
B33: Transfer to Lohith Reddy (capital allocation) | D33: 125000 | E33: Bank → Lohith | F33: Internal Transfer | G33: For acquisition & expenses
B34: Soft Restaurant License & Tools | D34: 15195 | E34: Soft App | F34: Software / License | G34: POS + mgmt tools
B35: Mercado Pago Terminal | D35: 500 | E35: Mercado Pago | F35: Equipment / POS | G35: POS terminal for payments
B41: KASHIGOUD TOTAL | D41: =SUM(D26:D33)
B43: D. PRE-OPENING EXPENSES — LOHITH REDDY
B44: Description | C44: Date | D44: Amount ($) | E44: Paid To | F44: Category | G44: Notes
B45: Advance Payment to Previous Owners | D45: 5000 | E45: Previous Owners | F45: Acquisition | G45: 5k advance on 390k purchase
B46: Notary Fees | D46: 15797 | E46: Notary Office | F46: Legal | G46: Legal fees for restaurant acquisition
B47: Poliza Juridica (Legal Policy) | D47: 5150 | E47: Legal / Insurance | F47: Legal | G47: Poliza Juridica — legal insurance policy
B48: Alejandra — Documentation Asst. | D48: 3000 | E48: Alejandra | F48: Professional Services | G48: Paperwork & documentation
B54: LOHITH TOTAL | D54: =SUM(D38:D46)
B56: E. PRE-OPENING EXPENSES — SHASHIREKHA BASAVARAJU
B57: Description | C57: Date | D57: Amount ($) | E57: Paid To | F57: Category | G57: Notes
B58: Transfer to Lohith Reddy (capital allocation) | D58: 100000 | E58: Bank → Lohith | F58: Internal Transfer | G58: For acquisition & expenses
B59: Temu items | D59: 2646 | E59: Temu | F59: Equipment / Supplies | G59: Temu items — restaurant supplies & equipment
B60: Board games for restaurant ambiance | D60: 745 | E60: Supplier | F60: Equipment / Supplies | G60: Board games for restaurant ambiance
B61: Special menu board
B62: Logo and sticker printing | D62: 845 | E62: Print Shop | F62: Branding / Signage | G62: Logo and sticker printing
B63: Sign boards, stationary, other decor | D63: 1555 | E63: China Shop | F63: Decor / Signage | G63: Sign boards, stationary, other decor
B66: Logo Box Repair / Fix | C66: 46176 | D66: 900 | E66: Supplier | F66: Branding / Signage | G66: Logo box repair — paid by Shashirekha
B67: SHASHIREKHA TOTAL
B69: F. GRAND SUMMARY — CAPITAL DEPLOYMENT
B70: Line Item
B71: Total Budget (All Partners) | C71: =SUM(D6:D8) | D71: =C63/$C$63 | E71: 100% of committed capital
B72: Restaurant Acquisition — Full Price | C72: =D13 | D72: =C64/$C$63 | E72: To be paid to previous owners
B73: → Advance Paid (by Lohith) | C73: =D14 | D73: =C65/$C$63 | E73: ✅ Already paid
B74: → Balance Remaining | C74: =D15 | D74: =C66/$C$63 | E74: ⏳ Pending — funded by transfers
B75: Kashigoud — Ops Expenses (excl. transfer) | C75: =D27+D28 | D75: =C67/$C$63 | E75: Soft license + terminal
B76: Kashigoud → Lohith Transfer | C76: 125000
B77: Lohith — All Pre-Opening Expenses | C77: =D47 | D77: =C69/$C$63 | E77: Advance + Notary + Poliza + Alejandra
B78: Shashirekha → Lohith Transfer | C78: 100000
B79: Shashirekha — Other Expenses | C79: =SUM(D52:D58) | D79: =C71/$C$63 | E79: Yellow rows above
B80: TOTAL CASH OUT (excl. internal transfers) | C80: =C64+C67+C69+C71 | D80: =C72/$C$63 | E80: Actual cash leaving the partnership
B81: REMAINING UNALLOCATED BUDGET
B83: G. REMAINING TRANSFERS DUE TO LOHITH REDDY | C83: G. REMAINING TRANSFERS DUE TO LOHITH REDDY | D83: G. REMAINING TRANSFERS DUE TO LOHITH REDDY | E83: G. REMAINING TRANSFERS DUE TO LOHITH REDDY | F83: G. REMAINING TRANSFERS DUE TO LOHITH REDDY | G83: G. REMAINING TRANSFERS DUE TO LOHITH REDDY
B84: Partner | C84: Total Budget ($) | D84: Already Transferred ($) | E84: Direct Expenses ($) | F84: Still Owed to Lohith ($) | G84: Status
B85: Kashigoud Patil | C85: ='Capital & Ownership'!D7 | D85: ='Capital & Ownership'!D26 | E85: ='Capital & Ownership'!D27+'Capital & Ownership'!D28 | F85: ='Capital & Ownership'!C77-'Capital & Ownership'!D77-'Capital & Ownership'!E77 | G85: ⏳ PENDING
B86: Shashirekha Basavaraju | C86: ='Capital & Ownership'!D8 | D86: ='Capital & Ownership'!D51 | E86: =SUM('Capital & Ownership'!D52:'Capital & Ownership'!D58) | F86: ='Capital & Ownership'!C78-'Capital & Ownership'!D78-'Capital & Ownership'!E78 | G86: ⏳ PENDING
B87: TOTAL | C87: =C77+C78 | D87: =D77+D78 | E87: =E77+E78 | F87: =F77+F78
B89: H. ACQUISITION PAYMENT — SPLIT BY OWNERSHIP SHARE ($385,000 BALANCE DUE) | C89: H. ACQUISITION PAYMENT — SPLIT BY OWNERSHIP SHARE ($385,000 BALANCE DUE) | D89: H. ACQUISITION PAYMENT — SPLIT BY OWNERSHIP SHARE ($385,000 BALANCE DUE) | E89: H. ACQUISITION PAYMENT — SPLIT BY OWNERSHIP SHARE ($385,000 BALANCE DUE) | F89: H. ACQUISITION PAYMENT — SPLIT BY OWNERSHIP SHARE ($385,000 BALANCE DUE) | G89: H. ACQUISITION PAYMENT — SPLIT BY OWNERSHIP SHARE ($385,000 BALANCE DUE)
B90: Partner | C90: Share % | D90: Share of $390k Total ($) | E90: Advance Credited ($) | F90: Balance Owed to Prev. Owners ($) | G90: Status
B91: Lohith Reddy | C91: 0.5 | D91: ='Capital & Ownership'!C6 | E91: =D83*'Capital & Ownership'!D13 | F91: ='Capital & Ownership'!D14 | G91: =E83-F83
B92: Kashigoud Patil | C92: 0.3 | D92: ='Capital & Ownership'!C7 | E92: =D84*'Capital & Ownership'!D13 | F92: 0 | G92: =E84-F84
B93: Shashirekha Basavaraju | C93: 0.2 | D93: ='Capital & Ownership'!C8 | E93: =D85*'Capital & Ownership'!D13 | F93: 0 | G93: =E85-F85
B94: TOTAL | C94: 1 | D94: =D83+D84+D85 | E94: =E83+E84+E85 | F94: =F83+F84+F85 | G94: =G83+G84+G85

Sheet 📊 Dashboard
A2: 🍽️ LOKA Cafe Restaurante | H2: Restaurant Manager — powered by Soft + Excel
B5: 📌 HOW TO USE: ① Each update, go to 📅 Daily Log → enter Date + Revenue + Orders from Soft App ② Fill 💸 Expenses for costs paid ③ Update 📦 Inventory when stock changes ④ This dashboard updates automatically
B7: 💰 REVENUE (auto-pulled from Daily Log)
B9: TODAY'S REVENUE | D9: WEEK REVENUE | F9: MONTH REVENUE | H9: TODAY'S EXPENSES | J9: TODAY'S NET PROFIT | L9: AVG TICKET
B10: ='📅 Daily Log'!F6 | D10: ='📅 Daily Log'!N6 | F10: ='📅 Daily Log'!O6 | H10: ='📅 Daily Log'!H6 | J10: ='📅 Daily Log'!I6 | L10: =IFERROR('📅 Daily Log'!F6/'📅 Daily Log'!G6,0)
B14: 📊 OPERATIONS
B16: TODAY'S ORDERS | D16: WEEK ORDERS | F16: PROFIT MARGIN % | H16: LOW STOCK ITEMS | J16: WEEK EXPENSES | L16: PENDING ORDERS
B17: ='📅 Daily Log'!G6 | D17: =IFERROR(SUMPRODUCT((ISNUMBER('📅 Daily Log'!$B$8:$B$500))*('📅 Daily Log'!$B$8:$B$500>=TODAY()-MOD(TODAY()-2,7))*('📅 Daily Log'!$B$8:$B$500<TODAY()-MOD(TODAY()-2,7)+7)*IF(ISNUMBER('📅 Daily Log'!$G$8:$G$500),'📅 Daily Log'!$G$8:$G$500,0)),0) | F17: =IFERROR('📅 Daily Log'!J6,0) | H17: ='📦 Inventory'!H5 | J17: ='📅 Daily Log'!P6 | L17: ='🚚 Suppliers'!H5
B21: 📅 LAST 10 DAYS (from Daily Log — updates automatically)
B22: Date | C22: Day | D22: Revenue ($) | E22: Orders | F22: Avg Ticket | G22: Expenses ($) | H22: Net Profit ($) | I22: Margin % | J22: Notes | K22: vs Prev Day
B23: ='📅 Daily Log'!B8 | C23: ='📅 Daily Log'!F8 | D23: ='📅 Daily Log'!G8 | E23: =IFERROR('📅 Daily Log'!F8/'📅 Daily Log'!G8,0) | F23: ='📅 Daily Log'!H8 | G23: ='📅 Daily Log'!I8 | H23: ='📅 Daily Log'!J8 | I23: ='📅 Daily Log'!K8 | J23: ='📅 Daily Log'!K8 | K23: —
B24: ='📅 Daily Log'!B9 | C24: ='📅 Daily Log'!F9 | D24: ='📅 Daily Log'!G9 | E24: =IFERROR('📅 Daily Log'!F9/'📅 Daily Log'!G9,0) | F24: ='📅 Daily Log'!H9 | G24: ='📅 Daily Log'!I9 | H24: ='📅 Daily Log'!J9 | I24: ='📅 Daily Log'!K9 | J24: ='📅 Daily Log'!K9 | K24: =IFERROR(IF(D24>D23,"▲ +"&TEXT(D24-D23,"$#,##0"),IF(D24<D23,"▼ "&TEXT(D24-D23,"$#,##0"),"— same")),"")
B25: ='📅 Daily Log'!B10 | C25: ='📅 Daily Log'!F10 | D25: ='📅 Daily Log'!G10 | E25: =IFERROR('📅 Daily Log'!F10/'📅 Daily Log'!G10,0) | F25: ='📅 Daily Log'!H10 | G25: ='📅 Daily Log'!I10 | H25: ='📅 Daily Log'!J10 | I25: ='📅 Daily Log'!K10 | J25: ='📅 Daily Log'!K10 | K25: =IFERROR(IF(D25>D24,"▲ +"&TEXT(D25-D24,"$#,##0"),IF(D25<D24,"▼ "&TEXT(D25-D24,"$#,##0"),"— same")),"")
B26: ='📅 Daily Log'!B11 | C26: ='📅 Daily Log'!F11 | D26: ='📅 Daily Log'!G11 | E26: =IFERROR('📅 Daily Log'!F11/'📅 Daily Log'!G11,0) | F26: ='📅 Daily Log'!H11 | G26: ='📅 Daily Log'!I11 | H26: ='📅 Daily Log'!J11 | I26: ='📅 Daily Log'!K11 | J26: ='📅 Daily Log'!K11 | K26: =IFERROR(IF(D26>D25,"▲ +"&TEXT(D26-D25,"$#,##0"),IF(D26<D25,"▼ "&TEXT(D26-D25,"$#,##0"),"— same")),"")
B27: ='📅 Daily Log'!B12 | C27: ='📅 Daily Log'!F12 | D27: ='📅 Daily Log'!G12 | E27: =IFERROR('📅 Daily Log'!F12/'📅 Daily Log'!G12,0) | F27: ='📅 Daily Log'!H12 | G27: ='📅 Daily Log'!I12 | H27: ='📅 Daily Log'!J12 | I27: ='📅 Daily Log'!K12 | J27: ='📅 Daily Log'!K12 | K27: =IFERROR(IF(D27>D26,"▲ +"&TEXT(D27-D26,"$#,##0"),IF(D27<D26,"▼ "&TEXT(D27-D26,"$#,##0"),"— same")),"")
B28: ='📅 Daily Log'!B13 | C28: ='📅 Daily Log'!F13 | D28: ='📅 Daily Log'!G13 | E28: =IFERROR('📅 Daily Log'!F13/'📅 Daily Log'!G13,0) | F28: ='📅 Daily Log'!H13 | G28: ='📅 Daily Log'!I13 | H28: ='📅 Daily Log'!J13 | I28: ='📅 Daily Log'!K13 | J28: ='📅 Daily Log'!K13 | K28: =IFERROR(IF(D28>D27,"▲ +"&TEXT(D28-D27,"$#,##0"),IF(D28<D27,"▼ "&TEXT(D28-D27,"$#,##0"),"— same")),"")
B29: ='📅 Daily Log'!B14 | C29: ='📅 Daily Log'!F14 | D29: ='📅 Daily Log'!G14 | E29: =IFERROR('📅 Daily Log'!F14/'📅 Daily Log'!G14,0) | F29: ='📅 Daily Log'!H14 | G29: ='📅 Daily Log'!I14 | H29: ='📅 Daily Log'!J14 | I29: ='📅 Daily Log'!K14 | J29: ='📅 Daily Log'!K14 | K29: =IFERROR(IF(D29>D28,"▲ +"&TEXT(D29-D28,"$#,##0"),IF(D29<D28,"▼ "&TEXT(D29-D28,"$#,##0"),"— same")),"")
B30: ='📅 Daily Log'!B15 | C30: ='📅 Daily Log'!F15 | D30: ='📅 Daily Log'!G15 | E30: =IFERROR('📅 Daily Log'!F15/'📅 Daily Log'!G15,0) | F30: ='📅 Daily Log'!H15 | G30: ='📅 Daily Log'!I15 | H30: ='📅 Daily Log'!J15 | I30: ='📅 Daily Log'!K15 | J30: ='📅 Daily Log'!K15 | K30: =IFERROR(IF(D30>D29,"▲ +"&TEXT(D30-D29,"$#,##0"),IF(D30<D29,"▼ "&TEXT(D30-D29,"$#,##0"),"— same")),"")
B31: ='📅 Daily Log'!B16 | C31: ='📅 Daily Log'!F16 | D31: ='📅 Daily Log'!G16 | E31: =IFERROR('📅 Daily Log'!F16/'📅 Daily Log'!G16,0) | F31: ='📅 Daily Log'!H16 | G31: ='📅 Daily Log'!I16 | H31: ='📅 Daily Log'!J16 | I31: ='📅 Daily Log'!K16 | J31: ='📅 Daily Log'!K16 | K31: =IFERROR(IF(D31>D30,"▲ +"&TEXT(D31-D30,"$#,##0"),IF(D31<D30,"▼ "&TEXT(D31-D30,"$#,##0"),"— same")),"")
B32: ='📅 Daily Log'!B17 | C32: ='📅 Daily Log'!F17 | D32: ='📅 Daily Log'!G17 | E32: =IFERROR('📅 Daily Log'!F17/'📅 Daily Log'!G17,0) | F32: ='📅 Daily Log'!H17 | G32: ='📅 Daily Log'!I17 | H32: ='📅 Daily Log'!J17 | I32: ='📅 Daily Log'!K17 | J32: ='📅 Daily Log'!K17 | K32: =IFERROR(IF(D32>D31,"▲ +"&TEXT(D32-D31,"$#,##0"),IF(D32<D31,"▼ "&TEXT(D32-D31,"$#,##0"),"— same")),"")
B34: ⚠️ INVENTORY ALERTS (from Inventory sheet)
B35: Ingredient | F35: Min Level | H35: Status | J35: Action Needed
B36: ='📦 Inventory'!B9 | E36: ='📦 Inventory'!E9 | G36: ='📦 Inventory'!F9 | I36: ='📦 Inventory'!J9 | K36: =IF('📦 Inventory'!E9=0,"🚫 Order immediately",IF('📦 Inventory'!E9<='📦 Inventory'!F9,"⚠️ Reorder soon","✅ OK"))
B37: ='📦 Inventory'!B10 | E37: ='📦 Inventory'!E10 | G37: ='📦 Inventory'!F10 | I37: ='📦 Inventory'!J10 | K37: =IF('📦 Inventory'!E10=0,"🚫 Order immediately",IF('📦 Inventory'!E10<='📦 Inventory'!F10,"⚠️ Reorder soon","✅ OK"))
B38: ='📦 Inventory'!B11 | E38: ='📦 Inventory'!E11 | G38: ='📦 Inventory'!F11 | I38: ='📦 Inventory'!J11 | K38: =IF('📦 Inventory'!E11=0,"🚫 Order immediately",IF('📦 Inventory'!E11<='📦 Inventory'!F11,"⚠️ Reorder soon","✅ OK"))
B39: ='📦 Inventory'!B12 | E39: ='📦 Inventory'!E12 | G39: ='📦 Inventory'!F12 | I39: ='📦 Inventory'!J12 | K39: =IF('📦 Inventory'!E12=0,"🚫 Order immediately",IF('📦 Inventory'!E12<='📦 Inventory'!F12,"⚠️ Reorder soon","✅ OK"))
B40: ='📦 Inventory'!B13 | E40: ='📦 Inventory'!E13 | G40: ='📦 Inventory'!F13 | I40: ='📦 Inventory'!J13 | K40: =IF('📦 Inventory'!E13=0,"🚫 Order immediately",IF('📦 Inventory'!E13<='📦 Inventory'!F13,"⚠️ Reorder soon","✅ OK"))
B42: 💼 CAPITAL & ACQUISITION STATUS — live from Capital & Ownership sheet
B44: TOTAL BUDGET | D44: TOTAL CASH OUT | F44: REMAINING BUDGET | H44: ACQUISITION PRICE | J44: ADVANCE PAID | L44: BALANCE PENDING
B45: ='Capital & Ownership'!C63 | D45: ='Capital & Ownership'!C72 | F45: ='Capital & Ownership'!C73 | H45: ='Capital & Ownership'!C64 | J45: ='Capital & Ownership'!C65 | L45: ='Capital & Ownership'!C66
B46: All 3 partners | D46: Excl. internal transfers | F46: Available for operations | H46: To previous owners | J46: ✅ Paid by Lohith | L46: ⏳ Outstanding
B48: 👥 OWNER CAPITAL SUMMARY
B49: OWNER | D49: SHARE % | F49: CAPITAL ($) | G49: ROLE | H49: EXPENSES ($) | J49: REMAINING ($) | L49: % SPENT
B50: ='Capital & Ownership'!B6 | D50: ='Capital & Ownership'!C6 | F50: ='Capital & Ownership'!D6 | G50: 50% — Managing Partner | H50: ='Capital & Ownership'!E6 | J50: ='Capital & Ownership'!F6 | L50: =IFERROR('Capital & Ownership'!E6/'Capital & Ownership'!D6,0)
B51: ='Capital & Ownership'!B7 | D51: ='Capital & Ownership'!C7 | F51: ='Capital & Ownership'!D7 | G51: 30% — Partner | H51: ='Capital & Ownership'!E7 | J51: ='Capital & Ownership'!F7 | L51: =IFERROR('Capital & Ownership'!E7/'Capital & Ownership'!D7,0)
B52: ='Capital & Ownership'!B8 | D52: ='Capital & Ownership'!C8 | F52: ='Capital & Ownership'!D8 | G52: 20% — Partner | H52: ='Capital & Ownership'!E8 | J52: ='Capital & Ownership'!F8 | L52: =IFERROR('Capital & Ownership'!E8/'Capital & Ownership'!D8,0)
B53: TOTAL | D53: ='Capital & Ownership'!C9 | F53: ='Capital & Ownership'!D9 | H53: ='Capital & Ownership'!E9 | J53: ='Capital & Ownership'!F9 | L53: =IFERROR('Capital & Ownership'!E9/'Capital & Ownership'!D9,0)
B55: 🧾 PRE-OPENING EXPENSES BREAKDOWN
B56: EXPENSE ITEM | E56: PAID BY | G56: AMOUNT ($) | I56: CATEGORY | K56: STATUS
B57: ='Capital & Ownership'!B13 | E57: All Partners | G57: ='Capital & Ownership'!D13 | I57: Acquisition | K57: ⚠️ Not Fully Paid
B58: ='Capital & Ownership'!B14 | E58: Lohith Reddy | G58: ='Capital & Ownership'!D14 | I58: Acquisition Advance | K58: ✅ Paid
B59: ='Capital & Ownership'!B27 | E59: Kashigoud Patil | G59: ='Capital & Ownership'!D27 | I59: Software / License | K59: ✅ Paid
B60: ='Capital & Ownership'!B28 | E60: Kashigoud Patil | G60: ='Capital & Ownership'!D28 | I60: Equipment | K60: ✅ Paid
B61: ='Capital & Ownership'!B39 | E61: Lohith Reddy | G61: ='Capital & Ownership'!D39 | I61: Legal / Notary | K61: ✅ Paid
B62: ='Capital & Ownership'!B40 | E62: Lohith Reddy | G62: ='Capital & Ownership'!D40 | I62: Legal / Insurance | K62: ✅ Paid
B63: ='Capital & Ownership'!B41 | E63: Lohith Reddy | G63: ='Capital & Ownership'!D41 | I63: Professional Services | K63: ✅ Paid
B64: ℹ️ Internal transfers: Kashigoud → Lohith $125,000 | Shashirekha → Lohith $100,000 (not counted as expenses — capital reallocation only)

Sheet 📅 Daily Log
A2: 📅 LOKA — DAILY LOG | I2: Enter 2 values from Soft App each day → everything else calculates
B5: ✏️ INSTRUCTIONS: Each time you open this file, add a new row below. Fill only the BLUE cells: 📌 Date | 💰 Revenue (from Soft App end-of-day report) | 🛒 Orders (from Soft App) | 📝 Notes (optional). All other columns calculate automatically.
F6: =SUMIFS($D$8:$D$500,$B$8:$B$500,TODAY())+SUMIFS($E$8:$E$500,$B$8:$B$500,TODAY())+SUMIFS($G$8:$G$500,$B$8:$B$500,TODAY()) | G6: =SUMIFS($G$8:$G$500,$B$8:$B$500,TODAY()) | H6: =SUMIFS($H$8:$H$500,$B$8:$B$500,TODAY()) | I6: =F6-H6 | J6: =IFERROR(I6/F6,0) | M6: =SUMPRODUCT((ISNUMBER($B$8:$B$500))*($B$8:$B$500>=TODAY()-MOD(TODAY()-2,7))*($B$8:$B$500<TODAY()-MOD(TODAY()-2,7)+7)*IF(ISNUMBER($F$8:$F$500),$F$8:$F$500,0)) | N6: =SUMPRODUCT((ISNUMBER($B$8:$B$500))*($B$8:$B$500>=TODAY()-MOD(TODAY()-2,7))*($B$8:$B$500<TODAY()-MOD(TODAY()-2,7)+7)*IF(ISNUMBER($F$8:$F$500),$F$8:$F$500,0)) | O6: =SUMPRODUCT((ISNUMBER($B$8:$B$500))*(MONTH($B$8:$B$500)=MONTH(TODAY()))*(YEAR($B$8:$B$500)=YEAR(TODAY()))*IF(ISNUMBER($F$8:$F$500),$F$8:$F$500,0)) | P6: =SUMPRODUCT((ISNUMBER($B$8:$B$500))*($B$8:$B$500>=TODAY()-MOD(TODAY()-2,7))*($B$8:$B$500<TODAY()-MOD(TODAY()-2,7)+7)*IF(ISNUMBER($H$8:$H$500),$H$8:$H$500,0)) | Q6: =M6-P6
B7: Date | C7: Day | D7: Card / Mercado Pago ($) | E7: Cash ($) | F7: Total Revenue ($) | G7: Transfer ($) | H7: Expenses $ | I7: Net Profit $ | J7: Margin % | K7: Notes | L7: Source | M7: WEEK PROFIT | N7: CUMUL. REVENUE | O7: MONTH REVENUE | P7: Week Expenses | Q7: Week Profit
B8: 18-May-2026 | C8: Mon | D8: 2229 | E8: 1460 | F8: =IFERROR(D8+E8+G8,0) | H8: 2629 | I8: =IFERROR(F8-H8,0) | J8: =IFERROR(I8/F8,0) | L8: Manual Bills
B9: 19-May-2026 | C9: Tue | D9: 2125 | E9: 1729 | F9: =IFERROR(D9+E9+G9,0) | H9: 30 | I9: =IFERROR(F9-H9,0) | J9: =IFERROR(I9/F9,0) | L9: Manual Bills
B10: 20-May-2026 | C10: Wed | D10: 1459 | E10: 2665 | F10: =IFERROR(D10+E10+G10,0) | H10: 3777 | I10: =IFERROR(F10-H10,0) | J10: =IFERROR(I10/F10,0) | L10: Manual Bills
B11: 21-May-2026 | C11: Thu | D11: 2570 | E11: 2163 | F11: =IFERROR(D11+E11+G11,0) | H11: 2434 | I11: =IFERROR(F11-H11,0) | J11: =IFERROR(I11/F11,0) | L11: Manual Bills
B12: 22-May-2026 | C12: Fri | D12: 1959 | E12: 2323 | F12: =IFERROR(D12+E12+G12,0) | H12: 1457 | I12: =IFERROR(F12-H12,0) | J12: =IFERROR(I12/F12,0) | L12: Manual Bills
B13: 23-May-2026 | C13: Sat | D13: 2044 | E13: 1758 | F13: =IFERROR(D13+E13+G13,0) | H13: 8953.43 | I13: =IFERROR(F13-H13,0) | J13: =IFERROR(I13/F13,0) | K13: Payroll week — John $3,250 + Debi $1,500 + Victor $666 + Tips $1,198 | L13: Manual Bills
B14: 24-May-2026 | C14: Sun | E14: 1198 | F14: =IFERROR(D14+E14+G14,0) | H14: 1076 | I14: =IFERROR(F14-H14,0) | J14: =IFERROR(I14/F14,0) | K14: 🔴 CLOSED — Sunday. Expenses are prep purchases for the week ahead. | L14: Manual Bills
B15: 25-May-2026 | C15: Mon | D15: 2106 | E15: 1624 | F15: =IFERROR(D15+E15+G15,0) | H15: 3021.45 | I15: =IFERROR(F15-H15,0) | J15: =IFERROR(I15/F15,0) | L15: Manual Bills
B16: 26-May-2026 | C16: Tue | D16: 1909 | E16: 2355 | F16: =IFERROR(D16+E16+G16,0) | H16: 1191.6 | I16: =IFERROR(F16-H16,0) | J16: =IFERROR(I16/F16,0) | L16: Manual Bills
B17: 27-May-2026 | C17: Wed | D17: 1956 | E17: 1665 | F17: =IFERROR(D17+E17+G17,0) | H17: 1073.22 | I17: =IFERROR(F17-H17,0) | J17: =IFERROR(I17/F17,0) | L17: Manual Bills
B18: 28-May-2026 | C18: Thu | D18: 1501 | E18: 2569 | F18: =IFERROR(D18+E18+G18,0) | H18: 1931.34 | I18: =IFERROR(F18-H18,0) | J18: =IFERROR(I18/F18,0) | L18: Manual Bills
B19: 29-May-2026 | C19: Fri | D19: 3369 | E19: 2717 | F19: =IFERROR(D19+E19+G19,0) | H19: 257.29 | I19: =IFERROR(F19-H19,0) | J19: =IFERROR(I19/F19,0) | L19: Manual Bills
B20: 30-May-2026 | C20: Sat | D20: 3457 | E20: 1146 | F20: =IFERROR(D20+E20+G20,0) | H20: 5974.3 | I20: =IFERROR(F20-H20,0) | J20: =IFERROR(I20/F20,0) | L20: Manual Bills
B21: 31-May-2026 | C21: Sun | E21: 893 | F21: =IFERROR(D21+E21+G21,0) | H21: 312 | I21: =IFERROR(F21-H21,0) | J21: =IFERROR(I21/F21,0) | L21: Manual Bills
B22: 01-Jun-2026 | C22: Mon | D22: 3433 | E22: 1276 | F22: =IFERROR(D22+E22+G22,0) | G22: 310 | H22: 6029.64 | I22: =IFERROR(F22-H22,0) | J22: =IFERROR(I22/F22,0) | L22: Manual Bills
B23: 02-Jun-2026 | C23: Tue | D23: 1240 | E23: 320 | F23: =IFERROR(D23+E23+G23,0) | G23: 283 | H23: 2379.11 | I23: =IFERROR(F23-H23,0) | J23: =IFERROR(I23/F23,0) | L23: Manual Bills
B24: 03-Jun-2026 | C24: Wed | D24: 1853 | E24: 1939 | F24: =IFERROR(D24+E24+G24,0) | G24: 120 | H24: 4033.86 | I24: =IFERROR(F24-H24,0) | J24: =IFERROR(I24/F24,0) | L24: Manual Bills
B25: 04-Jun-2026 | C25: Thu | D25: 2712 | E25: 1045 | F25: =IFERROR(D25+E25+G25,0) | H25: 20959.96 | I25: =IFERROR(F25-H25,0) | J25: =IFERROR(I25/F25,0) | L25: Manual Bills

Sheet 💸 Expenses
A2: 💸 LOKA — EXPENSES TRACKER | E2: Log every cost: ingredients, staff, utilities, supplies…
B5: TODAY | C5: THIS WEEK | D5: THIS MONTH | E5: INGREDIENTS | F5: STAFF | G5: UTILITIES | H5: TODAY TOTAL | I5: WEEK TOTAL
B6: =SUMIFS($F$8:$F$500,$B$8:$B$500,TODAY()) | C6: =SUMIFS($F$8:$F$500,$B$8:$B$500,">="&(TODAY()-WEEKDAY(TODAY(),2)+1),$B$8:$B$500,"<="&(TODAY()-WEEKDAY(TODAY(),2)+7)) | D6: =SUMIFS($F$8:$F$500,$B$8:$B$500,">="&DATE(YEAR(TODAY()),MONTH(TODAY()),1),$B$8:$B$500,"<"&DATE(YEAR(TODAY()),MONTH(TODAY())+1,1)) | E6: =SUMIF($E$8:$E$500,"Ingredients*",$F$8:$F$500) | F6: =SUMIF($E$8:$E$500,"Staff*",$F$8:$F$500) | G6: =SUMIF($E$8:$E$500,"Supplies*",$F$8:$F$500)+SUMIF($E$8:$E$500,"Utilities*",$F$8:$F$500) | H6: =SUMIFS($F$8:$F$500,$B$8:$B$500,TODAY()) | I6: =SUMIFS($F$8:$F$500,$B$8:$B$500,">="&(TODAY()-WEEKDAY(TODAY(),2)+1),$B$8:$B$500,"<="&(TODAY()-WEEKDAY(TODAY(),2)+7))
B7: Date | C7: Description | D7: Supplier | E7: Category | F7: Amount ($) | G7: Paid By | H7: Payment Method | I7: Status | J7: Notes
B8: 46160 | C8: Carne | D8: — | E8: Ingredients - Meat | F8: 420 | G8: Restaurant | H8: Cash | I8: ✅ Paid
B9: 46160 | C9: Basicos | D9: — | E9: Ingredients - Pantry | F9: 1068 | G9: Restaurant | H9: Cash | I9: ✅ Paid
B10: 46160 | C10: Real Pan Services | D10: Real Pan | E10: Ingredients - Bread | F10: 522 | G10: Restaurant | H10: Cash | I10: ✅ Paid
B11: 46160 | C11: Chedruai | D11: Chedraui | E11: Supermarket / General | F11: 129 | G11: Restaurant | H11: Cash | I11: ✅ Paid
B12: 46160 | C12: Vegetables | D12: Abastos | E12: Ingredients - Vegetables | F12: 400 | G12: Restaurant | H12: Cash | I12: ✅ Paid
B13: 46160 | C13: Vegetables | D13: — | E13: Ingredients - Vegetables | F13: 90 | G13: Restaurant | H13: Cash | I13: ✅ Paid
B14: 46161 | C14: Arroz | D14: — | E14: Ingredients - Pantry | F14: 30 | G14: Restaurant | H14: Cash | I14: ✅ Paid
B15: 46162 | C15: Lechuga | D15: — | E15: Ingredients - Vegetables | F15: 65 | G15: Restaurant | H15: Cash | I15: ✅ Paid
B16: 46162 | C16: Tortillas | D16: — | E16: Ingredients - Pantry | F16: 26 | G16: Restaurant | H16: Cash | I16: ✅ Paid
B17: 46162 | C17: Jamon Mexicana | D17: — | E17: Ingredients - Meat | F17: 88 | G17: Restaurant | H17: Cash | I17: ✅ Paid
B18: 46162 | C18: Carne | D18: — | E18: Ingredients - Meat | F18: 1104 | G18: Restaurant | H18: Cash | I18: ✅ Paid
B19: 46162 | C19: Salmon | D19: — | E19: Ingredients - Meat & Fish | F19: 397 | G19: Restaurant | H19: Cash | I19: ✅ Paid
... B46: 46165 | C46: Agua Natural | D46: — | E46: Supplies / Other | F46: 30 | G46: Restaurant | H46: Cash | I46: ✅ Paid
B47: 46165 | C47: John - Saldo Semana | D47: Nomina | E47: Staff - Salary | F47: 3250 | G47: Restaurant | H47: Cash | I47: ✅ Paid | J47: Head Chef — weekly salary Week 1
B48: 46165 | C48: Debi - Limpieza | D48: Nomina | E48: Staff - Salary | F48: 1500 | G48: Restaurant | H48: Cash | I48: ✅ Paid | J48: Cleaning staff — weekly salary Week 1
B49: 46165 | C49: Victor - Mesero (2 dias) | D49: Nomina | E49: Staff - Salary | F49: 666 | G49: Restaurant | H49: Cash | I49: ✅ Paid | J49: Waiter — 2 days salary Week 1
B50: 46165 | C50: Propinas - John (6 dias) | D50: Dist. propinas sem 1 | E50: Staff - Tips Distribution | F50: 515 | G50: Restaurant | H50: Cash | I50: ✅ Paid | J50: Tips distribution Week 1
B51: 46165 | C51: Propinas - Debi (6 dias) | D51: Dist. propinas sem 1 | E51: Staff - Tips Distribution | F51: 515 | G51: Restaurant | H51: Cash | I51: ✅ Paid | J51: Tips distribution Week 1
B52: 46165 | C52: Propinas - Victor (2 dias) | D52: Dist. propinas sem 1 | E52: Staff - Tips Distribution | F52: 168 | G52: Restaurant | H52: Cash | I52: ⏳ PENDING | J52: Yet to pay Victor — Week 1 tips
B53: 46165 | C53: Sal Fina (20 x 1 kg) | D53: Costco | E53: Ingredients - Pantry | F53: 408.17 | G53: Restaurant | H53: Card | I53: ✅ Paid | J53: Costco — Sal Fina 20/1KG
B54: 46165 | C54: Coca Cola (24 x 600ml) | D54: Costco | E54: Ingredients - Beverages | F54: 455.23 | G54: Restaurant | H54: Card | I54: ✅ Paid | J54: Costco — discount applied, total $844
B55: 46165 | C55: Leche Deslactosada (12 x 1LT) | D55: Sam's Club | E55: Ingredients - Dairy | F55: 317.13 | G55: Restaurant | H55: Card | I55: ✅ Paid | J55: Sam's Club — reimbursed to Shashirekha, settled
B56: 46165 | C56: Leche Alpura (12 x 1L) | D56: Sam's Club | E56: Ingredients - Dairy | F56: 317.13 | G56: Restaurant | H56: Card | I56: ✅ Paid | J56: Sam's Club — reimbursed to Shashirekha, settled
B57: 46165 | C57: Crema Ácida | D57: Sam's Club | E57: Ingredients - Dairy | F57: 250.63 | G57: Restaurant | H57: Card | I57: ✅ Paid | J57: Sam's Club — reimbursed to Shashirekha, settled
B58: 46165 | C58: Salsa / Tomate (12 x 600ml) | D58: Sam's Club | E58: Ingredients - Pantry | F58: 232.22 | G58: Restaurant | H58: Card | I58: ✅ Paid | J58: Sam's Club — reimbursed to Shashirekha, settled
B59: 46165 | C59: Champiñones (24 x 400ml) | D59: Sam's Club | E59: Ingredients - Vegetables | F59: 218.92 | G59: Restaurant | H59: Card | I59: ✅ Paid | J59: Sam's Club — reimbursed to Shashirekha, settled
B60: 46166 | C60: Guayabas Mediana | D60: Aviles Hernandez | E60: Ingredients - Fruit | F60: 120 | G60: Restaurant | H60: Cash | I60: ✅ Paid
B61: 46166 | C61: Jicamas + Pinas + Melon Chino | D61: El Matamoros | E61: Ingredients - Fruit | F61: 147 | G61: Restaurant | H61: Cash | I61: ✅ Paid
B62: 46166 | C62: Cilantro + Italiana | D62: Oscar Verduras | E62: Ingredients - Vegetables | F62: 100 | G62: Restaurant | H62: Cash | I62: ✅ Paid
B63: 46166 | C63: Habanero + Pepino | D63: Remision Formitec | E63: Ingredients - Vegetables | F63: 90 | G63: Restaurant | H63: Cash | I63: ✅ Paid
B64: 46166 | C64: Betabel (~1.9 kg) | D64: Nota Remision | E64: Ingredients - Vegetables | F64: 78 | G64: Restaurant | H64: Cash | I64: ✅ Paid
B65: 46166 | C65: Jitomate | D65: Brisia y Hermanos | E65: Ingredients - Vegetables | F65: 178 | G65: Restaurant | H65: Cash | I65: ✅ Paid
B66: 46166 | C66: Mango + Sandia | D66: Papayas Maradol | E66: Ingredients - Fruit | F66: 116 | G66: Restaurant | H66: Cash | I66: ✅ Paid
B67: 46166 | C67: Verduras variadas | D67: JP Verduras | E67: Ingredients - Vegetables | F67: 224 | G67: Restaurant | H67: Cash | I67: ✅ Paid
B68: 46166 | C68: Pimiento Morron | D68: Sin factura | E68: Ingredients - Vegetables | F68: 23 | G68: Restaurant | H68: Cash | I68: ✅ Paid | J68: No receipt — Sin factura
B69: 46167 | C69: Pan para Hamburguesa con Ajonjolí + Pan de Caja Arandano | D69: Real Abastos | E69: Ingredients - Bread | F69: 273 | G69: Restaurant | H69: Card | I69: ✅ Paid | J69: Real Sucursal Central de Abastos — 12 pcs hamburger buns + 3x900g bread
B70: 46167 | C70: Limonada / Naranjada / Tamarindo 1LT (18 pcs) | D70: Reca del Bajio | E70: Ingredients - Beverages | F70: 450 | G70: Restaurant | H70: Card | I70: ✅ Paid | J70: Mercado Pago — 6 Limonada + 6 Naranjada + 6 Tamarindo
B71: 46167 | C71: QsoCrema Lala 190g | D71: Chedraui Selecto | E71: Ingredients - Dairy | F71: 32 | G71: Restaurant | H71: Card | I71: ✅ Paid
B72: 46167 | C72: Tortillas Blanca (2.21 kg) | D72: Chedraui Selecto | E72: Ingredients - Pantry | F72: 28.73 | G72: Restaurant | H72: Card | I72: ✅ Paid
B73: 46167 | C73: Rosca de Nuez | D73: Chedraui Selecto | E73: Ingredients - Bread | F73: 89 | G73: Restaurant | H73: Card | I73: ✅ Paid
B74: 46167 | C74: Bolillo (6 pcs) | D74: Chedraui Selecto | E74: Ingredients - Bread | F74: 12.6 | G74: Restaurant | H74: Card | I74: ✅ Paid
B75: 46167 | C75: Salmon lonja (1.455 kg) | D75: Brisa del Mar | E75: Ingredients - Meat & Fish | F75: 494.7 | G75: Restaurant | H75: Cash | I75: ✅ Paid | J75: 1.455 kg x $340/kg
B76: 46167 | C76: Papas (4 bolsas) | D76: — | E76: Ingredients - Vegetables | F76: 440 | G76: Restaurant | H76: Cash | I76: ✅ Paid | J76: Remision handwritten
B77: 46167 | C77: Costillas cerdo | D77: — | E77: Ingredients - Meat | F77: 282 | G77: Restaurant | H77: Cash | I77: ✅ Paid | J77: Remision handwritten
B78: 46167 | C78: Azucar Est Posada 1K | D78: OXXO | E78: Ingredients - Pantry | F78: 25 | G78: Restaurant | H78: Card | I78: ✅ Paid | J78: Paid via Mercado Libre
B79: 46167 | C79: Pollo NutryEnt (4 packs, 8.29 kg) | D79: Chedraui Paseo | E79: Ingredients - Meat | F79: 323.36 | G79: Restaurant | H79: Card | I79: ✅ Paid | J79: 4 x PolloNutryEnt ~2kg each
B80: 46167 | C80: Naranja de Jugo (1.265 kg) | D80: Chedraui Paseo | E80: Ingredients - Fruit | F80: 37.82 | G80: Restaurant | H80: Card | I80: ✅ Paid
B81: 46167 | C81: Mango Paraiso (1.560 kg) | D81: Chedraui Paseo | E81: Ingredients - Fruit | F81: 45.24 | G81: Restaurant | H81: Card | I81: ✅ Paid
B82: 46167 | C82: Azucar Ref 10/1K + Pastel Chocolate | D82: Costco | E82: Ingredients - Pantry | F82: 488 | G82: Restaurant | H82: Card | I82: ✅ Paid | J82: Azucar $275.18 + Pastel $224.03 — discount $11.21 applied
B83: 46168 | C83: Arroz Extra LP 500G | D83: OXXO | E83: Ingredients - Pantry | F83: 47.6 | G83: Restaurant | H83: Card | I83: ✅ Paid | J83: OXXO Circunvalacion QRF
B84: 46168 | C84: Chapata Grande Sabores Varios (24) | D84: Real Abastos | E84: Ingredients - Bread | F84: 288 | G84: Restaurant | H84: Card | I84: ✅ Paid | J84: 24 pcs x $12 = $288
B85: 46168 | C85: Tilapia (~6.74 kg) | D85: Pescaderia El Faro | E85: Ingredients - Meat & Fish | F85: 244 | G85: Restaurant | H85: Cash | I85: ✅ Paid | J85: Nota El Faro — corrected from $944 to $244
B86: 46168 | C86: Bistek de Puerco | D86: Remision | E86: Ingredients - Meat | F86: 586 | G86: Restaurant | H86: Card | I86: ✅ Paid | J86: Remision + Getnet card terminal
B87: 46168 | C87: Tortillas Blancos | D87: — | E87: Ingredients - Pantry | F87: 26 | G87: Restaurant | H87: Cash | I87: ✅ Paid | J87: No bill — cash purchase
B88: 46169 | C88: Jamon Delicia Pierna Mandolin (2.005 kg) | D88: San Juan Salchichonerias | E88: Ingredients - Meat | F88: 170.22 | G88: Restaurant | H88: Card | I88: ✅ Paid | J88: Rappi delivery — 27 May
B89: 46169 | C89: Arroz La Posada 900g (x3, 2x1 promo) | D89: OXXO | E89: Ingredients - Pantry | F89: 60 | G89: Restaurant | H89: Card | I89: ✅ Paid | J89: OXXO Unity QRF — buy 2 get 1 promo
B90: 46169 | C90: Tres Leches Frutos Rojos | D90: Lecaroz 1972 | E90: Ingredients - Desserts | F90: 260 | G90: Restaurant | H90: Card | I90: ✅ Paid | J90: Panadería Circunvalacion
B91: 46169 | C91: Tocino | D91: Remision | E91: Ingredients - Meat | F91: 236 | G91: Restaurant | H91: Card | I91: ✅ Paid | J91: Remision + Getnet card terminal
B92: 46169 | C92: Tortillas Blancos | D92: — | E92: Ingredients - Pantry | F92: 52 | G92: Restaurant | H92: Cash | I92: ✅ Paid | J92: No bill — cash purchase
B93: 46169 | C93: Vegetables | D93: — | E93: Ingredients - Vegetables | F93: 295 | G93: Restaurant | H93: Cash | I93: ✅ Paid | J93: No bill — cash purchase
... B95: 46170 | C95: Muslo c/Hueso Amarillo + Elote + Cebolla | D95: H-E-B | E95: Ingredients - Meat | F95: 83.91 | G95: Restaurant | H95: Card | I95: ✅ Paid | J95: Net after return of $268.91 (chicken issue)
B96: 46170 | C96: QsoCrema Lala + Tortilla Amarilla | D96: Chedraui Selecto | E96: Ingredients - Dairy | F96: 56.11 | G96: Restaurant | H96: Card | I96: ✅ Paid
B97: 46170 | C97: Microfibra Formula (2 pcs) | D97: Chedraui Selecto | E97: Supplies / Other | F97: 23.2 | G97: Restaurant | H97: Card | I97: ✅ Paid | J97: Cleaning supplies
B98: 46170 | C98: Nutralat Milk 1.5L (x2) | D98: OXXO | E98: Ingredients - Dairy | F98: 48 | G98: Restaurant | H98: Card | I98: ✅ Paid | J98: OXXO Pathe QRF
B99: 46170 | C99: Muslo con Hueso (4.8 kg) | D99: Merjaliz | E99: Ingredients - Meat | F99: 336 | G99: Restaurant | H99: Cash | I99: ✅ Paid | J99: Mercado de Abastos — 4.8kg x $70
B100: 46170 | C100: Queso Panela Quinta Azul Granel (2.4 kg) | D100: CAQ | E100: Ingredients - Dairy | F100: 296.12 | G100: Restaurant | H100: Card | I100: ✅ Paid | J100: 2.4kg x $123.38
B101: 46170 | C101: Queso Gouda Menona (1 unit) | D101: Bodega del Queso | E101: Ingredients - Dairy | F101: 135 | G101: Restaurant | H101: Cash | I101: ✅ Paid | J101: Restaurant portion only — 1 of 2 units
B102: 46170 | C102: Lechuga Italiana | D102: — | E102: Ingredients - Vegetables | F102: 48 | G102: Restaurant | H102: Cash | I102: ✅ Paid | J102: No bill
B103: 46170 | C103: Hielo | D103: — | E103: Supplies / Other | F103: 100 | G103: Restaurant | H103: Cash | I103: ✅ Paid | J103: No bill
B104: 46170 | C104: Agua Natural | D104: — | E104: Supplies / Other | F104: 45 | G104: Restaurant | H104: Cash | I104: ✅ Paid | J104: No bill
B105: 46170 | C105: Potato (Papas) | D105: — | E105: Ingredients - Vegetables | F105: 200 | G105: Restaurant | H105: Cash | I105: ✅ Paid | J105: No bill
B106: 46170 | C106: Lechuga Italiana | D106: — | E106: Ingredients - Vegetables | F106: 30 | G106: Restaurant | H106: Cash | I106: ✅ Paid | J106: No bill
B107: 46171 | C107: Jitomate (2.030 kg) | D107: Super Fruterias Bermudez | E107: Ingredients - Vegetables | F107: 99.47 | G107: Restaurant | H107: Cash | I107: ✅ Paid | J107: 2.030kg x $49/kg
B108: 46171 | C108: Tortillas Blanca (3.875 kg) | D108: Chedraui Paseo | E108: Ingredients - Pantry | F108: 51.92 | G108: Restaurant | H108: Card | I108: ✅ Paid
B109: 46171 | C109: Concha Chocolate (3 pcs) | D109: Chedraui Paseo | E109: Ingredients - Bread | F109: 36 | G109: Restaurant | H109: Card | I109: ✅ Paid
B110: 46171 | C110: Rosca Marmoleada | D110: Chedraui Paseo | E110: Ingredients - Bread | F110: 69.9 | G110: Restaurant | H110: Card | I110: ✅ Paid
B111: 46172 | C111: Arroz La Posada 900g (4 pcs, 2x1 promo) | D111: OXXO Pathe QRF | E111: Ingredients - Pantry | F111: 60 | G111: Restaurant | H111: Card | I111: ✅ Paid | J111: 4 packs, buy 2 get 2 promo — $11.60 saving
B112: 46172 | C112: Frijol Bayos REF 430g | D112: OXXO Pathe QRF | E112: Ingredients - Pantry | F112: 17.9 | G112: Restaurant | H112: Card | I112: ✅ Paid | J112: $1.00 discount applied
B113: 46172 | C113: Huevo BCO Bachoco 12P | D113: OXXO Pathe QRF | E113: Ingredients - Pantry | F113: 36 | G113: Restaurant | H113: Cash | I113: ✅ Paid | J113: $8.50 discount applied — paid $50 cash change $14
B114: 46172 | C114: Frutas y Verduras variadas | D114: Fruteria Franco | E114: Ingredients - Fruit | F114: 220 | G114: Restaurant | H114: Card | I114: ✅ Paid | J114: Mercado Pago — Fruteria Franco
B115: 46172 | C115: Pollo Muslo | D115: — | E115: Ingredients - Meat | F115: 310 | G115: Restaurant | H115: Cash | I115: ✅ Paid | J115: No bill — cash purchase
B116: 46172 | C116: John — Saldo Semana (Week 2) | D116: Nomina | E116: Staff - Salary | F116: 3750 | G116: Restaurant | H116: Cash | I116: ✅ Paid | J116: Head Chef — weekly salary Week 2
B117: 46172 | C117: Duvi/Debi — Limpieza (Week 2) | D117: Nomina | E117: Staff - Salary | F117: 1500 | G117: Restaurant | H117: Cash | I117: ✅ Paid | J117: Cleaning staff — weekly salary Week 2
B118: 46172 | C118: Tomate (0.930 kg) | D118: Super Fruterias Bermudez | E118: Ingredients - Vegetables | F118: 18.6 | G118: Restaurant | H118: Cash | I118: ✅ Paid | J118: 0.930kg x $20/kg
B119: 46172 | C119: Jitomate (1.180 kg) | D119: Super Fruterias Bermudez | E119: Ingredients - Vegetables | F119: 57.8 | G119: Restaurant | H119: Cash | I119: ✅ Paid | J119: 1.180kg x $49/kg
B120: 46172 | C120: Cilantro (4 un) | D120: Super Fruterias Bermudez | E120: Ingredients - Vegetables | F120: 4 | G120: Restaurant | H120: Cash | I120: ✅ Paid | J120: 4 units x $1/un
B121: 46173 | C121: Aceite La Posada 800 (12 units, 2x1 promo) | D121: OXXO | E121: Ingredients - Pantry | F121: 312 | G121: Restaurant | H121: Card | I121: ✅ Paid | J121: $70.80 discount applied — Mercado Libre payment
B122: 46174 | C122: Propinas - John (Week 2) | D122: Nomina | E122: Staff - Tips Distribution | F122: 350 | G122: Restaurant | H122: Cash | I122: ✅ Paid | J122: Week 2 propinas — John
B123: 46174 | C123: Propinas - Duvi/Debi (Week 2) | D123: Nomina | E123: Staff - Tips Distribution | F123: 350 | G123: Restaurant | H123: Cash | I123: ✅ Paid | J123: Week 2 propinas — Duvi/Debi
B124: 46174 | C124: Azucar Morena 10/1 | D124: Costco | E124: Ingredients - Pantry | F124: 219.94 | G124: Restaurant | H124: Card | I124: ✅ Paid
B125: 46174 | C125: Atun DOL.AG 10/140 | D125: Costco | E125: Ingredients - Pantry | F125: 193.34 | G125: Restaurant | H125: Card | I125: ✅ Paid
B126: 46174 | C126: Mayonesa 3.7L (x2) | D126: Costco | E126: Ingredients - Pantry | F126: 468.52 | G126: Restaurant | H126: Card | I126: ✅ Paid | J126: 2 packs x $234.26
B127: 46174 | C127: Agua Mineral 12/600ml | D127: Costco | E127: Ingredients - Beverages | F127: 230.16 | G127: Restaurant | H127: Card | I127: ✅ Paid | J127: Net after $30.68 discount split
B128: 46174 | C128: Pastel Queso Guayaba | D128: Costco | E128: Ingredients - Bread | F128: 224.04 | G128: Restaurant | H128: Card | I128: ✅ Paid | J128: Net after discount allocation
B129: 46174 | C129: Arroz 10/900 (3 packs) | D129: Sam's Club | E129: Ingredients - Pantry | F129: 540 | G129: Restaurant | H129: Card | I129: ✅ Paid | J129: 3 x $184.14, discount -$12.42
B130: 46174 | C130: Arrachera Clarita | D130: Miscelanea LC La Cruz | E130: Ingredients - Meat | F130: 303 | G130: Restaurant | H130: Card | I130: ✅ Paid | J130: Getnet terminal
...

Sheet 📦 Inventory
A2: 📦 LOKA — INVENTORY | F2: Update stock levels when you receive deliveries or do stock checks
B5: TOTAL ITEMS | D5: ⚠️ LOW STOCK | E5: LOW STOCK # | F5: 🚫 OUT OF STOCK | H5: ALERT COUNT | J5: LAST UPDATED
B6: =COUNTA(B9:B200) | D6: =COUNTIF(J9:J200,"⚠️ LOW STOCK") | E6: =COUNTIF(J9:J200,"⚠️ LOW STOCK")+COUNTIF(J9:J200,"🚫 OUT OF STOCK") | F6: =COUNTIF(J9:J200,"🚫 OUT OF STOCK") | H6: =COUNTIF(J9:J200,"⚠️ LOW STOCK")+COUNTIF(J9:J200,"🚫 OUT OF STOCK") | J6: =TODAY()
B8: Item Name | Category | Unit | Min Stock | Current Stock | Last Ordered | Supplier | Status | Notes
B9: Carne de Res | C9: Ingredients - Meat | D9: kg | E9: 0 | J9: =IF(ISBLANK(F9),"—",IF(F9=0,"🚫 OUT OF STOCK",IF(F9<=E9,"⚠️ LOW STOCK","✅ OK")))
B10: Jamon Mexicano | C10: Ingredients - Meat | D10: kg | E10: 0 | J10: =IF(ISBLANK(F10),"—",IF(F10=0,"🚫 OUT OF STOCK",IF(F10<=E10,"⚠️ LOW STOCK","✅ OK")))
B11: Pollo | C11: Ingredients - Meat | D11: kg | E11: 0 | J11: =IF(ISBLANK(F11),"—",IF(F11=0,"🚫 OUT OF STOCK",IF(F11<=E11,"⚠️ LOW STOCK","✅ OK")))
B12: Chuletas de Carne | C12: Ingredients - Meat | D12: kg | E12: 0 | J12: =IF(ISBLANK(F12),"—",IF(F12=0,"🚫 OUT OF STOCK",IF(F12<=E12,"⚠️ LOW STOCK","✅ OK")))
B13: Costillas de Cerdo | C13: Ingredients - Meat | D13: kg | E13: 0 | J13: =IF(ISBLANK(F13),"—",IF(F13=0,"🚫 OUT OF STOCK",IF(F13<=E13,"⚠️ LOW STOCK","✅ OK")))
B14: Salmon | C14: Ingredients - Meat & Fish | D14: kg | E14: 0 | J14: =IF(ISBLANK(F14),"—",IF(F14=0,"🚫 OUT OF STOCK",IF(F14<=E14,"⚠️ LOW STOCK","✅ OK")))
B15: Filete de Mojarra | C15: Ingredients - Meat & Fish | D15: kg | E15: 0 | J15: =IF(ISBLANK(F15),"—",IF(F15=0,"🚫 OUT OF STOCK",IF(F15<=E15,"⚠️ LOW STOCK","✅ OK")))
B16: Papas | C16: Ingredients - Vegetables | D16: kg | E16: 0 | J16: =IF(ISBLANK(F16),"—",IF(F16=0,"🚫 OUT OF STOCK",IF(F16<=E16,"⚠️ LOW STOCK","✅ OK")))
B17: Lechuga | C17: Ingredients - Vegetables | D17: pcs | E17: 0 | J17: =IF(ISBLANK(F17),"—",IF(F17=0,"🚫 OUT OF STOCK",IF(F17<=E17,"⚠️ LOW STOCK","✅ OK")))
B18: Jitomate | C18: Ingredients - Vegetables | D18: kg | E18: 0 | J18: =IF(ISBLANK(F18),"—",IF(F18=0,"🚫 OUT OF STOCK",IF(F18<=E18,"⚠️ LOW STOCK","✅ OK")))
B19: Cilantro | C19: Ingredients - Vegetables | D19: pcs | E19: 0 | J19: =IF(ISBLANK(F19),"—",IF(F19=0,"🚫 OUT OF STOCK",IF(F19<=E19,"⚠️ LOW STOCK","✅ OK")))
B20: Italiana | C20: Ingredients - Vegetables | D20: pcs | E20: 0 | J20: =IF(ISBLANK(F20),"—",IF(F20=0,"🚫 OUT OF STOCK",IF(F20<=E20,"⚠️ LOW STOCK","✅ OK")))
... B73: Huevo Bachoco | C73: Ingredients - Pantry | D73: pcs | E73: 0 | J73: =IF(ISBLANK(F73),"—",IF(F73=0,"🚫 OUT OF STOCK",IF(F73<=E73,"⚠️ LOW STOCK","✅ OK")))

Sheet 👥 Staff & Payroll
A2: 👥 LOKA — STAFF & PAYROLL | G2: Weekly schedule + auto payroll calculation
B6: STAFF SCHEDULE — Week of: | E6: =TODAY()-WEEKDAY(TODAY(),2)+1
B7: Staff Name | C7: Role | D7: Daily Rate ($) | E7: Mon | F7: Tue | G7: Wed | H7: Thu | I7: Fri | J7: Sat | K7: Sun | L7: Days Worked | M7: Week Pay ($)
B8: John | C8: Head Chef | D8: 625 | E8: Full Day | F8: Full Day | G8: Full Day | H8: Full Day | I8: Full Day | J8: Full Day | K8: Day Off | L8: =COUNTIF(E8:K8,"Full Day") | M8: =L8*D8
B9: Debi | C9: Cleaner | D9: 250 | E9: Full Day | F9: Full Day | G9: Full Day | H9: Full Day | I9: Full Day | J9: Full Day | K9: Day Off | L9: =COUNTIF(E9:K9,"Full Day") | M9: =L9*D9
B10: Victor (INACTIVE) | C10: Mesero — Left after Week 1 | D10: 0 | E10: — | F10: — | G10: — | H10: — | I10: — | J10: — | K10: — | L10: 0 | M10: 0
B11: Judith | C11: Mesera / Waitress | D11: TBD — confirm weekly rate | E11: 46174 | F11: ✅ Active | G11: Started Mon 1 Jun 2026 — absent Wed 3 Jun
B20: MONTHLY PAYROLL PROJECTION
B21: Staff Name | C21: Role | D21: Week Pay ($) | E21: x Weeks/Month | F21: Monthly ($) | G21: IMSS / Benefits % | H21: Total Monthly Cost ($) | I21: Notes
B22: =B8 | C22: Head Chef | D22: =M8 | E22: 4 | F22: =D21*E21 | G22: 0.08 | H22: =F21*(1+G21)
B23: =B9 | C23: Sous Chef | D23: =M9 | E23: 4 | F23: =D22*E22 | G23: 0.08 | H23: =F22*(1+G22)
B24: =B10 | C24: Waiter 1 | D24: =M10 | E24: 4 | F24: =D23*E23 | G24: 0.08 | H24: =F23*(1+G23)
B25: =B11 | C25: Waiter 2 | D25: =M11 | E25: 4 | F25: =D24*E24 | G25: 0.08 | H25: =F24*(1+G24)
B26: =B12 | C26: Barista | D26: =M12 | E26: 4 | F26: =D25*E25 | G26: 0.08 | H26: =F25*(1+G25)
B27: =B13 | C27: Cashier | D27: =M13 | E27: 4 | F27: =D26*E26 | G27: 0.08 | H27: =F26*(1+G26)
B28: =B14 | C28: Kitchen Helper | D28: =M14 | E28: 4 | F28: =D27*E27 | G28: 0.08 | H28: =F27*(1+G27)
B29: =B15 | C29: Cleaner | D29: =M15 | E29: 4 | F29: =D28*E28 | G29: 0.08 | H29: =F28*(1+G28)
B30: TOTAL MONTHLY PAYROLL COST | H30: =SUM(H21:H28)
B33: ── WEEKLY FIXED COSTS & BREAK-EVEN TARGETS ──
B34: COST ITEM | C34: WEEKLY ($) | D34: MONTHLY EST. ($) | E34: NOTES
B35: John — Head Chef Salary | C35: 3750 | D35: 15000 | E35: Confirmed weekly rate
B36: Debi — Limpieza Salary | C36: 1500 | D36: 6000 | E36: Confirmed weekly rate
B37: Rent + Maintenance (actual — $20,000/mo) | C37: 5000 | D37: 20000 | E37: Confirmed — $20,000/month actual
B38: Utilities — Electricity + Gas (estimated) | C38: 1000 | D38: 4000 | E38: ⏳ Approx — bills pending · electricity + gas
B39: TOTAL FIXED COSTS (current) | C39: =SUM(C34:C37) | D39: =SUM(D34:D37) | E39: Before ingredients & supplies
B41: ── WITH MESERO / WAITER — ✅ JUDITH HIRED (1 Jun 2026) ──
B42: Mesero — Waiter Salary (est.) | C42: 2,000–2,500 | E42: Approx range when position filled
B43: TOTAL FIXED COSTS (with Mesero) | C43: TBD — confirm salary | E43: Judith salary TBD — update break-even once confirmed
B45: ── BREAK-EVEN & WEEKLY REVENUE TARGETS ──
B46: SCENARIO | C46: Fixed Costs ($) | D46: Avg Variable Costs ($) | E46: MIN Weekly Revenue ($) | F46: MIN Daily Revenue ($) | G46: Current Avg/Day ($) | H46: STATUS
B47: Without Mesero (NOW) | C47: 11250 | D47: 10500 | E47: 21750 | F47: 3625 | G47: 4011 | H47: ✅ Above break-even — revised down from $3,792 → $3,625/day
B48: With Mesero (~$2,250) | C48: 13500 | D48: 10500 | E48: 24000 | F48: 4000 | G48: 4011 | H48: ⚠️ Still below — need +$-11/day when mesero hired
B49: Safety buffer (+15%) | C49: 11250 | D49: 10500 | E49: 25012 | F49: 4169 | G49: 4011 | H49: Target for healthy buffer: $4,169/day
B51: NOTES:
B52: Variable costs = avg ingredients + supplies per week based on Weeks 1-2 actual data (~$10,500)
B53: Break-even revised: Rent+Maintenance confirmed $20,000/mo · Utilities est. $4,000/mo → Total overhead $24,000/mo
B54: Min daily (no mesero): $3,625 · With mesero: $4,000 · Comfortable target: $4,169+/day
B55: Utilities (electricity+gas) ~$4,000/mo is ESTIMATED — update when bills arrive
B59: ── LOHITH PERSONAL LEDGER — OWNER BALANCE TRACKER ──
B60: Date | C60: Description | D60: Type | E60: Spent by Lohith ($) | F60: Transferred to Lohith ($) | G60: Running Balance ($) | H60: Status | I60: Notes
B61: 46174 | C61: Telmex Internet Bill (Mayo) | D61: Expense - Personal | E61: 349 | G61: =IFERROR(E59-F59,0) | H61: ⏳ Reimburse | I61: Paid by Lohith — ⏳ Reimburse
B62: 46174 | C62: Customer Transfer — Jun 1 | D62: Transfer Received | F62: 310 | G62: =IFERROR(G59+E60-F60,0) | H62: ✅ | I62: ✅ Received in Lohith account
B63: 46175 | C63: Customer Transfer — Jun 2 | D63: Transfer Received | F63: 283 | G63: =IFERROR(G60+E61-F61,0) | H63: ✅ | I63: ✅ Received in Lohith account
B64: 46176 | C64: Customer Transfer — Jun 3 | D64: Transfer Received | F64: 120 | G64: =IFERROR(G61+E62-F62,0) | H64: ✅ | I64: ✅ Received in Lohith account
B65: 46177 | C65: Personal expenses — Huevos, Ajonjoli, Verduras | D65: Expense - Personal | E65: 358 | G65: =IFERROR(G62+E63-F63,0) | H65: ⏳ Reimburse | I65: $69 Huevos + $44 Ajonjoli Blanco + $45 Ajonjoli Negro + $200 Verduras
B66: 46177 | C66: Cash settlement — $6 added to restaurant | D66: Expense - Personal | E66: 6 | G66: =IFERROR(G63+E64-F64,0) | H66: ✅ Settled | I66: Lohith added $6 cash to restaurant — balance now ZERO
B67: TOTALS & CURRENT BALANCE | E67: =SUM(E59:E62) | F67: =SUM(F59:F62) | G67: =G64 | H67: =IF(G62>0,"⏳ Restaurant owes Lohith",IF(G62<0,"💵 Lohith holds restaurant funds","✅ Zero balance"))
B69: HOW TO USE:
B70: Add new rows above TOTALS. Spent by Lohith = restaurant expenses he paid personally.
B71: Transferred to Lohith = customer bank transfers received in his personal account.
B72: Positive balance = restaurant owes Lohith. Negative = Lohith holds restaurant funds.

Sheet 🚚 Suppliers
A2: 🚚 LOKA — SUPPLIER ORDERS | F2: Track purchase orders from suppliers
B5: TOTAL ORDERS | C5: PENDING | D5: IN TRANSIT | E5: RECEIVED | F5: MONTH SPEND | G5: PENDING VALUE | H5: PENDING COUNT
B6: =COUNTA(C9:C308)-1 | C6: =COUNTIF(K9:K308,"Pending") | D6: =COUNTIF(K9:K308,"In Transit") | E6: =COUNTIF(K9:K308,"Received") | F6: =SUMIF(K9:K308,"Received",J9:J308) | G6: =SUMIF(K9:K308,"Pending",J9:J308) | H6: =COUNTIF(K9:K308,"Pending")+COUNTIF(K9:K308,"In Transit")

Sheet 📋 Supplier Directory
B2: 📋 LOKA — SUPPLIER DIRECTORY
B3: Contact list for all regular suppliers
B6: Supplier Name | C6: Contact / Phone | D6: Products Supplied | E6: Location / Address | F6: Notes
B7: Girigallo | C7: 442-249-4707 | D7: Pollo | E7: Islas Aleutianas 134, Loma Linda, C.P 76070
B8: Alico | C8: 442-796-8876 | D8: Carne de hamburguesa, Papas, Boneless | E8: Cerro de las Campanas 173, Col. Las Americas
B9: Reca (Repartidor) | C9: 442-679-6651 | D9: Aguas Avia / Bebidas | E9: — | F9: Delivery supplier
B10: Toluco | C10: — | D10: Desechables (Plasticos) | E10: Plásticos Desechables el Toluco, C/ 15 de Mayo 189, La Santa Cruz, Centro, 76020 Santiago de Querétaro
B11: Bodega del Queso | C11: 442-114-0827 | D11: Queso, Jamon, Crema | E11: Avenida Universidad 119, Los Cedros, 76165 Santiago de Querétaro, Qro.
B12: Panadería Real | C12: 442-379-1880 | D12: Pan hamburguesa, Mayonesa, Arrachera, Sandwhich | E12: Plaza Capuchinas 149, Central de Abasto, Querétaro | F12: Also supplies at Brisa del Mar area
B13: Etrusca | C13: 442-234-5077 | D13: Sabores de Frappe, Matcha, Taro | E13: Café Etrusca Querétaro, Av. Tecnológico 10-Sur, Niños Héroes, 76010 Santiago de Querétaro
B16: Note: Additional suppliers recorded in expenses — Brisa del Mar, Chedraui, Costco, Real Abastos, OXXO, Pescadería El Faro

Sheet 📈 Monthly P&L
A2: 📈 LOKA — MONTHLY P&L | E2: Revenue & Expense summary — fill monthly totals from Daily Log & Expenses
B6: YEAR: | C6: 2025
C7: 2026

Sheet 📥 Pending Income
B2: LOKA CAFE RESTAURANTE — PENDING INCOME / RECEIVABLES | C2: LOKA CAFE RESTAURANTE — PENDING INCOME / RECEIVABLES | D2: LOKA CAFE RESTAURANTE — PENDING INCOME / RECEIVABLES | E2: LOKA CAFE RESTAURANTE — PENDING INCOME / RECEIVABLES | F2: LOKA CAFE RESTAURANTE — PENDING INCOME / RECEIVABLES | G2: LOKA CAFE RESTAURANTE — PENDING INCOME / RECEIVABLES | H2: LOKA CAFE RESTAURANTE — PENDING INCOME / RECEIVABLES | I2: LOKA CAFE RESTAURANTE — PENDING INCOME / RECEIVABLES
B4: Date Served | C4: Client | D4: Description | E4: Qty | F4: Unit Price ($) | G4: Total Amount ($) | H4: Status | I4: Notes
B5: 21-May-2026 | C5: Government Finances Dept. | D5: Catering order — 25 plates | E5: 25 | F5: 140 | G5: 3500 | H5: ⏳ NOT YET PAID | I5: Awaiting payment — follow up with client
B7: TOTAL PENDING | G7: 3500

Sheet 📊 Weekly Closing
B2: 📊 LOKA — WEEKLY CLOSING & PROPINAS
B3: Every Sunday night: enter closing balances to calculate propinas pool for the week
B6: ── WEEK 1 CLOSING SUMMARY (Sunday 25 May 2026) ──
B7: METRIC | D7: VALUE ($) | F7: NOTES
B8: Total Week Revenue (18–23 May) | D8: 24484 | F8: Card $12,386 + Cash $12,098
B9: Total Week Expenses (incl. propinas) | D9: 18157 | F9: All costs 18–24 May
B10: → Propinas Distributed | D10: 1030 | F10: John $515 + Debi $515
B11: → Propinas Pending | D11: 168 | F11: Victor $168 — yet to pay
B12: → Total Propinas | D12: 1198 | F12: To be paid from closing balance
B13: Total Expenses EXCL. Propinas | D13: 16959 | F13: Operating costs only
B14: Net Income (excl. propinas) | D14: 7525 | F14: =Revenue - Expenses excl. propinas
B16: ── SUNDAY NIGHT CLOSING BALANCE ──
B17: Mercado Pago Balance | D17: 5553 | F17: Incl. MP commission already deducted
B18: Cash in Hand | D18: 3170 | F18: Physical cash end of week
B19: Total Closing Balance | D19: 8723 | F19: MP + Cash
B21: ── PROPINAS CALCULATION ──
B22: Propinas Pool | D22: 1198 | F22: =Closing Balance - Net (excl. propinas)
B24: ── PROPINAS DISTRIBUTION ──
B25: Staff Name | C25: Role | D25: Days Worked | F25: Propinas Amount ($) | G25: Paid?
B26: John | C26: Head Chef | D26: 6 | F26: 515 | G26: ✅ Paid
B27: Debi | C27: Limpieza | D27: 6 | F27: 515 | G27: ✅ Paid
B28: Victor | C28: Mesero | D28: 2 | F28: 168 | G28: ⏳ PENDING
B29: TOTAL PROPINAS | F29: 1198
B30: Remaining after distribution | F30: 0 | G30: ← Should be 0 or rolled to next week
B34: ── WEEK 2 CLOSING SUMMARY (Sunday 31 May 2026) ──
B35: METRIC | C35: VALUE ($) | D35: NOTES
B36: Total Week Revenue (25–30 May) | D36: Fill from Daily Log
B37: Total Week Expenses (incl. propinas)
B38: → Propinas Distributed
B39: → Propinas Pending
B40: → Total Propinas
B41: Total Expenses EXCL. Propinas
B42: Net Income (excl. propinas)
B44: ── SUNDAY NIGHT CLOSING BALANCE ──
B45: Mercado Pago Balance | D45: Enter Sunday night amount
B46: Cash in Hand | D46: Enter Sunday night amount
B47: Total Closing Balance | D47: =MP + Cash
B49: ── PROPINAS CALCULATION ──
B50: Propinas Pool | D50: =Closing Balance - Net (excl. propinas)
B52: ── PROPINAS DISTRIBUTION ──
B53: Staff Name | C53: Role | D53: Days Worked | F53: Propinas Amount ($) | G53: Paid?
B54: John | C54: Head Chef
B55: Debi | C55: Limpieza
B56: Mesero (Vacant) | C56: — No waiter currently | D56: 0 | F56: 0 | G56: N/A
B57: TOTAL PROPINAS
B58: Remaining after distribution | G58: ← Should be 0 or rolled to next week
